Workbook

Sheet Inputs
A1: Venture Global (VG) model v7 - inputs (blue = input, yellow = key assumption)
A3: Share price, Oct 7 2026 close ($) | B3: 13.05
A4: Diluted shares (bn) | B4: 2.643
A5: Tax rate | B5: 0.19
A6: Discount rate, contracted cash and capex | B6: 0.07
A7: Discount rate, open cargoes | B7: 0.1
A8: Cost of net debt | B8: 0.063
A9: Net debt end-2026 ($bn) | B9: 40.449574
A10: Series A preferred liquidation ($bn) | B10: 3
A11: Preferred dividend ($bn/yr) | B11: 0.268
A12: Minority share of EBITDA ($bn/yr) | B12: 0.16
A13: BP adjustment ($bn) | B13: 1.4985
A14: Common dividend ($bn/yr) | B14: 0.39968
... A27: Contract run-off year | B27: 2049
A29: 2026 all-in cost per MMBtu (calibrated to guidance) | B29: =(Inputs!$B$15-Inputs!$B$16)*Inputs!$B$17/Inputs!$B$15+Inputs!$B$16*Inputs!$B$18/Inputs!$B$15-Inputs!$B$19*1000/Inputs!$B$15 -> 1.1474088
A30: Underlying cost per MMBtu ex basis | B30: =Inputs!$B$29-Inputs!$B$20*1000/Inputs!$B$15 -> 0.91643126
A32: Annual inputs
A33: Item | B33: 2027 | C33: 2028 | D33: 2029 | E33: 2030 | F33: 2031
A34: Volume (TBtu) | B34: 2220 | C34: 3330 | D34: 4255 | E34: 4420 | F34: 4420
A35: Open volume (TBtu) | B35: 675 | C35: 1625 | D35: 2475 | E35: 1900 | F35: 1664
A36: CME futures fee, JKM method ($/MMBtu) | B36: 14.921554 | C36: 8.051875 | D36: 5.2044458 | E36: 3.8404875 | F36: 2.49655
A37: Contract fee ($/MMBtu) | B37: 3 | C37: 2.6 | D37: 2.45 | E37: 2.45 | F37: 2.45
A38: Plaquemines basis cost ($bn) | B38: 0.435 | C38: 0.2175 | D38: 0 | E38: 0 | F38: 0
A39: Committed capex ($bn) | B39: 10 | C39: 8 | D39: 5 | E39: 2 | F39: 1
A40: D&A ($bn) | B40: 1.25 | C40: 1.6 | D40: 2 | E40: 2.4 | F40: 2.6

Sheet Model
A1: Annual model, central case ($bn unless stated)
A2: Year | B2: 2027 | C2: 2028 | D2: 2029 | E2: 2030 | F2: 2031
A3: Volume (TBtu) | B3: =Inputs!B$34 -> 2220 | C3: =Inputs!C$34 -> 3330 | D3: =Inputs!D$34 -> 4255 | E3: =Inputs!E$34 -> 4420 | F3: =Inputs!F$34 -> 4420
A4: Open volume (TBtu) | B4: =Inputs!B$35 -> 675 | C4: =Inputs!C$35 -> 1625 | D4: =Inputs!D$35 -> 2475 | E4: =Inputs!E$35 -> 1900 | F4: =Inputs!F$35 -> 1664
A5: Contracted volume (TBtu) | B5: =B3-B4 -> 1545 | C5: =C3-C4 -> 1705 | D5: =D3-D4 -> 1780 | E5: =E3-E4 -> 2520 | F5: =F3-F4 -> 2756
A6: Contracted margin before costs | B6: =B5*Inputs!B$37/1000 -> 4.635 | C6: =C5*Inputs!C$37/1000 -> 4.433 | D6: =D5*Inputs!D$37/1000 -> 4.361 | E6: =E5*Inputs!E$37/1000 -> 6.174 | F6: =F5*Inputs!F$37/1000 -> 6.7522
A7: CP2 contract premium | B7: =IF(2027>=2030,MAX(0,B5-Inputs!$B$24)*Inputs!$B$21/1000,0) -> 0 | C7: =IF(2028>=2030,MAX(0,C5-Inputs!$B$24)*Inputs!$B$21/1000,0) -> 0 | D7: =IF(2029>=2030,MAX(0,D5-Inputs!$B$24)*Inputs!$B$21/1000,0) -> 0 | E7: =IF(2030>=2030,MAX(0,E5-Inputs!$B$24)*Inputs!$B$21/1000,0) -> 0.384 | F7: =IF(2031>=2030,MAX(0,F5-Inputs!$B$24)*Inputs!$B$21/1000,0) -> 0.4784
A8: Open margin before costs | B8: =B4*Inputs!B$36/1000 -> 10.072049 | C8: =C4*Inputs!C$36/1000 -> 13.084297 | D8: =D4*Inputs!D$36/1000 -> 12.881003 | E8: =E4*Inputs!E$36/1000 -> 7.2969263 | F8: =F4*Inputs!F$36/1000 -> 4.1542592
A9: Operating cost | B9: =Inputs!$B$30*B3/1000+Inputs!B$38 -> 2.4694774 | C9: =Inputs!$B$30*C3/1000+Inputs!C$38 -> 3.2692161 | D9: =Inputs!$B$30*D3/1000+Inputs!D$38 -> 3.899415 | E9: =Inputs!$B$30*E3/1000+Inputs!E$38 -> 4.0506262 | F9: =Inputs!$B$30*F3/1000+Inputs!F$38 -> 4.0506262
A10: EBITDA | B10: =B6+B7+B8-B9 -> 12.237572 | C10: =C6+C7+C8-C9 -> 14.248081 | D10: =D6+D7+D8-D9 -> 13.342588 | E10: =E6+E7+E8-E9 -> 9.8043001 | F10: =F6+F7+F8-F9 -> 7.334233
A11: Cost on contracted volume | B11: =B9*B5/B3 -> 1.7186228 | C11: =C9*C5/C3 -> 1.6738779 | D11: =D9*D5/D3 -> 1.6312477 | E11: =E9*E5/E3 -> 2.3094068 | F11: =F9*F5/F3 -> 2.5256846
A12: Cost on open volume | B12: =B9*B4/B3 -> 0.75085462 | C12: =C9*C4/C3 -> 1.5953382 | D12: =D9*D4/D3 -> 2.2681674 | E12: =E9*E4/E3 -> 1.7412194 | F12: =F9*F4/F3 -> 1.5249416
A13: Contracted EBITDA | B13: =B6+B7-B11 -> 2.9163772 | C13: =C6+C7-C11 -> 2.7591221 | D13: =D6+D7-D11 -> 2.7297523 | E13: =E6+E7-E11 -> 4.2485932 | F13: =F6+F7-F11 -> 4.7049154
A14: Open EBITDA | B14: =B8-B12 -> 9.3211944 | C14: =C8-C12 -> 11.488959 | D14: =D8-D12 -> 10.612836 | E14: =E8-E12 -> 5.5557068 | F14: =F8-F12 -> 2.6293176
A15: D&A | B15: =Inputs!B$40 -> 1.25 | C15: =Inputs!C$40 -> 1.6 | D15: =Inputs!D$40 -> 2 | E15: =Inputs!E$40 -> 2.4 | F15: =Inputs!F$40 -> 2.6
A16: Interest on opening net debt | B16: =Inputs!$B$9*Inputs!$B$8 -> 2.5483232 | C16: =B26*Inputs!$B$8 -> 2.7240547 | D16: =C26*Inputs!$B$8 -> 2.6765664 | E16: =D26*Inputs!$B$8 -> 2.4802712 | F16: =E26*Inputs!$B$8 -> 2.2619268
A17: Pre-tax income | B17: =B10-B15-B16 -> 8.4392485 | C17: =C10-C15-C16 -> 9.9240261 | D17: =D10-D15-D16 -> 8.666022 | E17: =E10-E15-E16 -> 4.9240289 | F17: =F10-F15-F16 -> 2.4723062
A18: Tax | B18: =Inputs!$B$5*MAX(0,B17) -> 1.6034572 | C18: =Inputs!$B$5*MAX(0,C17) -> 1.885565 | D18: =Inputs!$B$5*MAX(0,D17) -> 1.6465442 | E18: =Inputs!$B$5*MAX(0,E17) -> 0.93556549 | F18: =Inputs!$B$5*MAX(0,F17) -> 0.46973818
A19: Preferred and minority | B19: =Inputs!$B$11+Inputs!$B$12 -> 0.428 | C19: =Inputs!$B$11+Inputs!$B$12 -> 0.428 | D19: =Inputs!$B$11+Inputs!$B$12 -> 0.428 | E19: =Inputs!$B$11+Inputs!$B$12 -> 0.428 | F19: =Inputs!$B$11+Inputs!$B$12 -> 0.428
A20: Net income to common | B20: =B17-B18-B19 -> 6.4077913 | C20: =C17-C18-C19 -> 7.6104612 | D20: =D17-D18-D19 -> 6.5914778 | E20: =E17-E18-E19 -> 3.5604634 | F20: =F17-F18-F19 -> 1.574568
A21: EPS ($) | B21: =B20/Inputs!$B$4 -> 2.4244386 | C21: =C20/Inputs!$B$4 -> 2.8794783 | D21: =D20/Inputs!$B$4 -> 2.4939379 | E21: =E20/Inputs!$B$4 -> 1.3471295 | F21: =F20/Inputs!$B$4 -> 0.59575029
A22: Cash tax | B22: =Inputs!$B$5*MAX(0,B10-B16-(1+0.3*0)) -> 1.6509572 | C22: =Inputs!$B$5*MAX(0,C10-C16-(1+0.3*1)) -> 1.942565 | D22: =Inputs!$B$5*MAX(0,D10-D16-(1+0.3*2)) -> 1.7225442 | E22: =Inputs!$B$5*MAX(0,E10-E16-(1+0.3*3)) -> 1.0305655 | F22: =Inputs!$B$5*MAX(0,F10-F16-(1+0.3*4)) -> 0.54573818
A23: Capex | B23: =Inputs!B$39 -> 10 | C23: =Inputs!C$39 -> 8 | D23: =Inputs!D$39 -> 5 | E23: =Inputs!E$39 -> 2 | F23: =Inputs!F$39 -> 1
A24: Common dividend | B24: =Inputs!$B$14 -> 0.39968 | C24: =Inputs!$B$14 -> 0.39968 | D24: =Inputs!$B$14 -> 0.39968 | E24: =Inputs!$B$14 -> 0.39968 | F24: =Inputs!$B$14 -> 0.39968
A25: Free cash flow after dividends | B25: =B10-B16-B22-B23-B19-B24 -> -2.7893887 | C25: =C10-C16-C22-C23-C19-C24 -> 0.75378115 | D25: =D10-D16-D22-D23-D19-D24 -> 3.1157978 | E25: =E10-E16-E22-E23-E19-E24 -> 3.4657834 | F25: =F10-F16-F22-F23-F19-F24 -> 2.698888
A26: Closing net debt | B26: =Inputs!$B$9-B25 -> 43.238963 | C26: =B26-C25 -> 42.485182 | D26: =C26-D25 -> 39.369384 | E26: =D26-E25 -> 35.9036 | F26: =E26-F25 -> 33.204712
A27: Net debt / EBITDA (x) | B27: =B26/B10 -> 3.533296 | C27: =C26/C10 -> 2.9818179 | D27: =D26/D10 -> 2.9506556 | E27: =E26/E10 -> 3.6620259 | F27: =F26/F10 -> 4.5273599
A28: Year index t | B28: =1 -> 1 | C28: =2 -> 2 | D28: =3 -> 3 | E28: =4 -> 4 | F28: =5 -> 5
A29: Discount factor, contracted | B29: =1/(1+Inputs!$B$6)^B28 -> 0.93457944 | C29: =1/(1+Inputs!$B$6)^C28 -> 0.87343873 | D29: =1/(1+Inputs!$B$6)^D28 -> 0.81629788 | E29: =1/(1+Inputs!$B$6)^E28 -> 0.76289521 | F29: =1/(1+Inputs!$B$6)^F28 -> 0.71298618
A30: Discount factor, open | B30: =1/(1+Inputs!$B$7)^B28 -> 0.90909091 | C30: =1/(1+Inputs!$B$7)^C28 -> 0.82644628 | D30: =1/(1+Inputs!$B$7)^D28 -> 0.7513148 | E30: =1/(1+Inputs!$B$7)^E28 -> 0.68301346 | F30: =1/(1+Inputs!$B$7)^F28 -> 0.62092132
A31: Discount factor from end-2028, contracted | B31: =IF(1>2,1/(1+Inputs!$B$6)^(1-2),0) -> 0 | C31: =IF(2>2,1/(1+Inputs!$B$6)^(2-2),0) -> 0 | D31: =IF(3>2,1/(1+Inputs!$B$6)^(3-2),0) -> 0.93457944 | E31: =IF(4>2,1/(1+Inputs!$B$6)^(4-2),0) -> 0.87343873 | F31: =IF(5>2,1/(1+Inputs!$B$6)^(5-2),0) -> 0.81629788
A32: Discount factor from end-2028, open | B32: =IF(1>2,1/(1+Inputs!$B$7)^(1-2),0) -> 0 | C32: =IF(2>2,1/(1+Inputs!$B$7)^(2-2),0) -> 0 | D32: =IF(3>2,1/(1+Inputs!$B$7)^(3-2),0) -> 0.90909091 | E32: =IF(4>2,1/(1+Inputs!$B$7)^(4-2),0) -> 0.82644628 | F32: =IF(5>2,1/(1+Inputs!$B$7)^(5-2),0) -> 0.7513148

Sheet Valuation
A1: Sum of the parts ($bn unless stated)
A3: PV contracted cash 2027-31 | B3: =SUMPRODUCT((Model!$B$13:$F$13*(1-Inputs!$B$5)+Inputs!$B$5*Model!$B$15:$F$15)*Model!$B$29:$F$29) -> 12.80503
A4: PV open cargoes 2027-31 | B4: =SUMPRODUCT(Model!$B$14:$F$14*(1-Inputs!$B$5)*Model!$B$30:$F$30) -> 25.409395
A5: PV committed capex | B5: =-SUMPRODUCT(Model!$B$23:$F$23*Model!$B$29:$F$29) -> -22.65357
A6: PV contracted annuity 2032-2049 | B6: =((Model!$F$5*(Inputs!$B$23-Inputs!$B$30)/1000+MAX(0,Model!$F$5-Inputs!$B$24)*Inputs!$B$21/1000-Inputs!$B$25*Model!$F$5/Model!$F$3)*(1-Inputs!$B$5)+Inputs!$B$5*Inputs!$B$26)*(1-(1+Inputs!$B$6)^-(Inputs!$B$27-2031))/Inputs!$B$6/(1+Inputs!$B$6)^5 -> 27.253007
A7: PV open cargoes from 2032 | B7: =(Model!$F$4*(Inputs!$B$22-Inputs!$B$30)/1000-Inputs!$B$25*(1-Model!$F$5/Model!$F$3))*(1-Inputs!$B$5)/Inputs!$B$7/(1+Inputs!$B$7)^5 -> 19.728509
A8: PV contracted volume turning open after 2049 | B8: =(Model!$F$5*(Inputs!$B$22-Inputs!$B$30)/1000)*(1-Inputs!$B$5)/Inputs!$B$7/(1+Inputs!$B$7)^(5+(Inputs!$B$27-2031)) -> 6.4409881
A9: Less net debt end-2026 | B9: =-Inputs!$B$9 -> -40.449574
A10: Less preferred | B10: =-Inputs!$B$10 -> -3
A11: Less Calcasieu minority | B11: =-Inputs!$B$12*(1-Inputs!$B$5)/Inputs!$B$6 -> -1.8514286
A12: Less BP adjustment | B12: =-Inputs!$B$13 -> -1.4985
A13: Equity value today | B13: =SUM(B3:B12) -> 22.183856
A14: Value per share today ($) | B14: =B13/Inputs!$B$4 -> 8.3934379
A15: Value at end-2028
A16: PV contracted cash 2029-31 | B16: =SUMPRODUCT((Model!$B$13:$F$13*(1-Inputs!$B$5)+Inputs!$B$5*Model!$B$15:$F$15)*Model!$B$31:$F$31) -> 9.3398411
A17: PV open cargoes 2029-31 | B17: =SUMPRODUCT(Model!$B$14:$F$14*(1-Inputs!$B$5)*Model!$B$32:$F$32) -> 13.134127
A18: PV capex 2029-31 | B18: =-SUMPRODUCT(Model!$B$23:$F$23*Model!$B$31:$F$31) -> -7.2360725
A19: PV contracted annuity 2032-2049 | B19: =((Model!$F$5*(Inputs!$B$23-Inputs!$B$30)/1000+MAX(0,Model!$F$5-Inputs!$B$24)*Inputs!$B$21/1000-Inputs!$B$25*Model!$F$5/Model!$F$3)*(1-Inputs!$B$5)+Inputs!$B$5*Inputs!$B$26)*(1-(1+Inputs!$B$6)^-(Inputs!$B$27-2031))/Inputs!$B$6/(1+Inputs!$B$6)^3 -> 31.201968
A20: PV open cargoes from 2032 | B20: =(Model!$F$4*(Inputs!$B$22-Inputs!$B$30)/1000-Inputs!$B$25*(1-Model!$F$5/Model!$F$3))*(1-Inputs!$B$5)/Inputs!$B$7/(1+Inputs!$B$7)^3 -> 23.871496
A21: PV contracted volume turning open after 2049 | B21: =(Model!$F$5*(Inputs!$B$22-Inputs!$B$30)/1000)*(1-Inputs!$B$5)/Inputs!$B$7/(1+Inputs!$B$7)^(3+(Inputs!$B$27-2031)) -> 7.7935955
A22: Less net debt end-2028 | B22: =-Model!$C$26 -> -42.485182
A23: Less preferred | B23: =-Inputs!$B$10 -> -3
A24: Less Calcasieu minority | B24: =-Inputs!$B$12*(1-Inputs!$B$5)/Inputs!$B$6 -> -1.8514286
A25: Less BP adjustment | B25: =-Inputs!$B$13 -> -1.4985
A26: Value per share at end-2028 ($) = 24-month target | B26: =SUM(B16:B25)/Inputs!$B$4 -> 11.074478
A27: Implied equity return a year, incl. dividends | B27: =((B26+2*0.16)/B14)^(1/2.23)-1 -> 0.14691487
A28: Share price ($) | B28: =Inputs!$B$3 -> 13.05
A29: Value per share per $1 of long-run fee | B29: =((Model!$F$4/1000)*(1-Inputs!$B$5)/Inputs!$B$7/(1+Inputs!$B$7)^5+(Model!$F$5/1000)*(1-Inputs!$B$5)/Inputs!$B$7/(1+Inputs!$B$7)^(5+(Inputs!$B$27-2031)))/Inputs!$B$4 -> 4.1097558
A30: Long-run fee the price needs ($/MMBtu) | B30: =Inputs!$B$22+(B28-B14)/B29 -> 4.6330508

Sheet Grid
A1: Value per share today: long-run fee from 2032 (rows) x flat cost per MMBtu (columns), no basis cost
A3: Long-run fee \ cost | B3: 1.15 | C3: 0.92 | D3: 0.75 | E3: 0.6
A4: 2.5 | B4: =(SUMPRODUCT(((Model!$B$6:$F$6+Model!$B$7:$F$7-B$3*Model!$B$5:$F$5/1000)*(1-Inputs!$B$5)+Inputs!$B$5*Model!$B$15:$F$15)*Model!$B$29:$F$29)+SUMPRODUCT((Model!$B$4:$F$4*Inputs!$B$36:$F$36/1000-B$3*Model!$B$4:$F$4/1000)*(1-Inputs!$B$5)*Model!$B$30:$F$30)-SUMPRODUCT(Model!$B$23:$F$23*Model!$B$29:$F$29)+((Model!$F$5*(Inputs!$B$23-B$3)/1000+MAX(0,Model!$F$5-Inputs!$B$24)*Inputs!$B$21/1000-Inputs!$B$25*Model!$F$5/Model!$F$3)*(1-Inputs!$B$5)+Inputs!$B$5*Inputs!$B$26)*(1-(1+Inputs!$B$6)^-(Inputs!$B$27-2031))/Inputs!$B$6/(1+Inputs!$B$6)^5+(Model!$F$4*($A4-B$3)/1000-Inputs!$B$25*(1-Model!$F$5/Model!$F$3))*(1-Inputs!$B$5)/Inputs!$B$7/(1+Inputs!$B$7)^5+(Model!$F$5*($A4-B$3)/1000)*(1-Inputs!$B$5)/Inputs!$B$7/(1+Inputs!$B$7)^(5+(Inputs!$B$27-2031))-Inputs!$B$9-Inputs!$B$10-Inputs!$B$12*(1-Inputs!$B$5)/Inputs!$B$6-Inputs!$B$13)/Inputs!$B$4 -> 1.0568791 | C4: =(SUMPRODUCT(((Model!$B$6:$F$6+Model!$B$7:$F$7-C$3*Model!$B$5:$F$5/1000)*(1-Inputs!$B$5)+Inputs!$B$5*Model!$B$15:$F$15)*Model!$B$29:$F$29)+SUMPRODUCT((Model!$B$4:$F$4*Inputs!$B$36:$F$36/1000-C$3*Model!$B$4:$F$4/1000)*(1-Inputs!$B$5)*Model!$B$30:$F$30)-SUMPRODUCT(Model!$B$23:$F$23*Model!$B$29:$F$29)+((Model!$F$5*(Inputs!$B$23-C$3)/1000+MAX(0,Model!$F$5-Inputs!$B$24)*Inputs!$B$21/1000-Inputs!$B$25*Model!$F$5/Model!$F$3)*(1-Inputs!$B$5)+Inputs!$B$5*Inputs!$B$26)*(1-(1+Inputs!$B$6)^-(Inputs!$B$27-2031))/Inputs!$B$6/(1+Inputs!$B$6)^5+(Model!$F$4*($A4-C$3)/1000-Inputs!$B$25*(1-Model!$F$5/Model!$F$3))*(1-Inputs!$B$5)/Inputs!$B$7/(1+Inputs!$B$7)^5+(Model!$F$5*($A4-C$3)/1000)*(1-Inputs!$B$5)/Inputs!$B$7/(1+Inputs!$B$7)^(5+(Inputs!$B$27-2031))-Inputs!$B$9-Inputs!$B$10-Inputs!$B$12*(1-Inputs!$B$5)/Inputs!$B$6-Inputs!$B$13)/Inputs!$B$4 -> 4.4118773 | D4: =(SUMPRODUCT(((Model!$B$6:$F$6+Model!$B$7:$F$7-D$3*Model!$B$5:$F$5/1000)*(1-Inputs!$B$5)+Inputs!$B$5*Model!$B$15:$F$15)*Model!$B$29:$F$29)+SUMPRODUCT((Model!$B$4:$F$4*Inputs!$B$36:$F$36/1000-D$3*Model!$B$4:$F$4/1000)*(1-Inputs!$B$5)*Model!$B$30:$F$30)-SUMPRODUCT(Model!$B$23:$F$23*Model!$B$29:$F$29)+((Model!$F$5*(Inputs!$B$23-D$3)/1000+MAX(0,Model!$F$5-Inputs!$B$24)*Inputs!$B$21/1000-Inputs!$B$25*Model!$F$5/Model!$F$3)*(1-Inputs!$B$5)+Inputs!$B$5*Inputs!$B$26)*(1-(1+Inputs!$B$6)^-(Inputs!$B$27-2031))/Inputs!$B$6/(1+Inputs!$B$6)^5+(Model!$F$4*($A4-D$3)/1000-Inputs!$B$25*(1-Model!$F$5/Model!$F$3))*(1-Inputs!$B$5)/Inputs!$B$7/(1+Inputs!$B$7)^5+(Model!$F$5*($A4-D$3)/1000)*(1-Inputs!$B$5)/Inputs!$B$7/(1+Inputs!$B$7)^(5+(Inputs!$B$27-2031))-Inputs!$B$9-Inputs!$B$10-Inputs!$B$12*(1-Inputs!$B$5)/Inputs!$B$6-Inputs!$B$13)/Inputs!$B$4 -> 6.8916586 | E4: =(SUMPRODUCT(((Model!$B$6:$F$6+Model!$B$7:$F$7-E$3*Model!$B$5:$F$5/1000)*(1-Inputs!$B$5)+Inputs!$B$5*Model!$B$15:$F$15)*Model!$B$29:$F$29)+SUMPRODUCT((Model!$B$4:$F$4*Inputs!$B$36:$F$36/1000-E$3*Model!$B$4:$F$4/1000)*(1-Inputs!$B$5)*Model!$B$30:$F$30)-SUMPRODUCT(Model!$B$23:$F$23*Model!$B$29:$F$29)+((Model!$F$5*(Inputs!$B$23-E$3)/1000+MAX(0,Model!$F$5-Inputs!$B$24)*Inputs!$B$21/1000-Inputs!$B$25*Model!$F$5/Model!$F$3)*(1-Inputs!$B$5)+Inputs!$B$5*Inputs!$B$26)*(1-(1+Inputs!$B$6)^-(Inputs!$B$27-2031))/Inputs!$B$6/(1+Inputs!$B$6)^5+(Model!$F$4*($A4-E$3)/1000-Inputs!$B$25*(1-Model!$F$5/Model!$F$3))*(1-Inputs!$B$5)/Inputs!$B$7/(1+Inputs!$B$7)^5+(Model!$F$5*($A4-E$3)/1000)*(1-Inputs!$B$5)/Inputs!$B$7/(1+Inputs!$B$7)^(5+(Inputs!$B$27-2031))-Inputs!$B$9-Inputs!$B$10-Inputs!$B$12*(1-Inputs!$B$5)/Inputs!$B$6-Inputs!$B$13)/Inputs!$B$4 -> 9.079701
A5: 3 | B5: =(SUMPRODUCT(((Model!$B$6:$F$6+Model!$B$7:$F$7-B$3*Model!$B$5:$F$5/1000)*(1-Inputs!$B$5)+Inputs!$B$5*Model!$B$15:$F$15)*Model!$B$29:$F$29)+SUMPRODUCT((Model!$B$4:$F$4*Inputs!$B$36:$F$36/1000-B$3*Model!$B$4:$F$4/1000)*(1-Inputs!$B$5)*Model!$B$30:$F$30)-SUMPRODUCT(Model!$B$23:$F$23*Model!$B$29:$F$29)+((Model!$F$5*(Inputs!$B$23-B$3)/1000+MAX(0,Model!$F$5-Inputs!$B$24)*Inputs!$B$21/1000-Inputs!$B$25*Model!$F$5/Model!$F$3)*(1-Inputs!$B$5)+Inputs!$B$5*Inputs!$B$26)*(1-(1+Inputs!$B$6)^-(Inputs!$B$27-2031))/Inputs!$B$6/(1+Inputs!$B$6)^5+(Model!$F$4*($A5-B$3)/1000-Inputs!$B$25*(1-Model!$F$5/Model!$F$3))*(1-Inputs!$B$5)/Inputs!$B$7/(1+Inputs!$B$7)^5+(Model!$F$5*($A5-B$3)/1000)*(1-Inputs!$B$5)/Inputs!$B$7/(1+Inputs!$B$7)^(5+(Inputs!$B$27-2031))-Inputs!$B$9-Inputs!$B$10-Inputs!$B$12*(1-Inputs!$B$5)/Inputs!$B$6-Inputs!$B$13)/Inputs!$B$4 -> 3.111757 | C5: =(SUMPRODUCT(((Model!$B$6:$F$6+Model!$B$7:$F$7-C$3*Model!$B$5:$F$5/1000)*(1-Inputs!$B$5)+Inputs!$B$5*Model!$B$15:$F$15)*Model!$B$29:$F$29)+SUMPRODUCT((Model!$B$4:$F$4*Inputs!$B$36:$F$36/1000-C$3*Model!$B$4:$F$4/1000)*(1-Inputs!$B$5)*Model!$B$30:$F$30)-SUMPRODUCT(Model!$B$23:$F$23*Model!$B$29:$F$29)+((Model!$F$5*(Inputs!$B$23-C$3)/1000+MAX(0,Model!$F$5-Inputs!$B$24)*Inputs!$B$21/1000-Inputs!$B$25*Model!$F$5/Model!$F$3)*(1-Inputs!$B$5)+Inputs!$B$5*Inputs!$B$26)*(1-(1+Inputs!$B$6)^-(Inputs!$B$27-2031))/Inputs!$B$6/(1+Inputs!$B$6)^5+(Model!$F$4*($A5-C$3)/1000-Inputs!$B$25*(1-Model!$F$5/Model!$F$3))*(1-Inputs!$B$5)/Inputs!$B$7/(1+Inputs!$B$7)^5+(Model!$F$5*($A5-C$3)/1000)*(1-Inputs!$B$5)/Inputs!$B$7/(1+Inputs!$B$7)^(5+(Inputs!$B$27-2031))-Inputs!$B$9-Inputs!$B$10-Inputs!$B$12*(1-Inputs!$B$5)/Inputs!$B$6-Inputs!$B$13)/Inputs!$B$4 -> 6.4667552 | D5: =(SUMPRODUCT(((Model!$B$6:$F$6+Model!$B$7:$F$7-D$3*Model!$B$5:$F$5/1000)*(1-Inputs!$B$5)+Inputs!$B$5*Model!$B$15:$F$15)*Model!$B$29:$F$29)+SUMPRODUCT((Model!$B$4:$F$4*Inputs!$B$36:$F$36/1000-D$3*Model!$B$4:$F$4/1000)*(1-Inputs!$B$5)*Model!$B$30:$F$30)-SUMPRODUCT(Model!$B$23:$F$23*Model!$B$29:$F$29)+((Model!$F$5*(Inputs!$B$23-D$3)/1000+MAX(0,Model!$F$5-Inputs!$B$24)*Inputs!$B$21/1000-Inputs!$B$25*Model!$F$5/Model!$F$3)*(1-Inputs!$B$5)+Inputs!$B$5*Inputs!$B$26)*(1-(1+Inputs!$B$6)^-(Inputs!$B$27-2031))/Inputs!$B$6/(1+Inputs!$B$6)^5+(Model!$F$4*($A5-D$3)/1000-Inputs!$B$25*(1-Model!$F$5/Model!$F$3))*(1-Inputs!$B$5)/Inputs!$B$7/(1+Inputs!$B$7)^5+(Model!$F$5*($A5-D$3)/1000)*(1-Inputs!$B$5)/Inputs!$B$7/(1+Inputs!$B$7)^(5+(Inputs!$B$27-2031))-Inputs!$B$9-Inputs!$B$10-Inputs!$B$12*(1-Inputs!$B$5)/Inputs!$B$6-Inputs!$B$13)/Inputs!$B$4 -> 8.9465365 | E5: =(SUMPRODUCT(((Model!$B$6:$F$6+Model!$B$7:$F$7-E$3*Model!$B$5:$F$5/1000)*(1-Inputs!$B$5)+Inputs!$B$5*Model!$B$15:$F$15)*Model!$B$29:$F$29)+SUMPRODUCT((Model!$B$4:$F$4*Inputs!$B$36:$F$36/1000-E$3*Model!$B$4:$F$4/1000)*(1-Inputs!$B$5)*Model!$B$30:$F$30)-SUMPRODUCT(Model!$B$23:$F$23*Model!$B$29:$F$29)+((Model!$F$5*(Inputs!$B$23-E$3)/1000+MAX(0,Model!$F$5-Inputs!$B$24)*Inputs!$B$21/1000-Inputs!$B$25*Model!$F$5/Model!$F$3)*(1-Inputs!$B$5)+Inputs!$B$5*Inputs!$B$26)*(1-(1+Inputs!$B$6)^-(Inputs!$B$27-2031))/Inputs!$B$6/(1+Inputs!$B$6)^5+(Model!$F$4*($A5-E$3)/1000-Inputs!$B$25*(1-Model!$F$5/Model!$F$3))*(1-Inputs!$B$5)/Inputs!$B$7/(1+Inputs!$B$7)^5+(Model!$F$5*($A5-E$3)/1000)*(1-Inputs!$B$5)/Inputs!$B$7/(1+Inputs!$B$7)^(5+(Inputs!$B$27-2031))-Inputs!$B$9-Inputs!$B$10-Inputs!$B$12*(1-Inputs!$B$5)/Inputs!$B$6-Inputs!$B$13)/Inputs!$B$4 -> 11.134579
A6: 3.5 | B6: =(SUMPRODUCT(((Model!$B$6:$F$6+Model!$B$7:$F$7-B$3*Model!$B$5:$F$5/1000)*(1-Inputs!$B$5)+Inputs!$B$5*Model!$B$15:$F$15)*Model!$B$29:$F$29)+SUMPRODUCT((Model!$B$4:$F$4*Inputs!$B$36:$F$36/1000-B$3*Model!$B$4:$F$4/1000)*(1-Inputs!$B$5)*Model!$B$30:$F$30)-SUMPRODUCT(Model!$B$23:$F$23*Model!$B$29:$F$29)+((Model!$F$5*(Inputs!$B$23-B$3)/1000+MAX(0,Model!$F$5-Inputs!$B$24)*Inputs!$B$21/1000-Inputs!$B$25*Model!$F$5/Model!$F$3)*(1-Inputs!$B$5)+Inputs!$B$5*Inputs!$B$26)*(1-(1+Inputs!$B$6)^-(Inputs!$B$27-2031))/Inputs!$B$6/(1+Inputs!$B$6)^5+(Model!$F$4*($A6-B$3)/1000-Inputs!$B$25*(1-Model!$F$5/Model!$F$3))*(1-Inputs!$B$5)/Inputs!$B$7/(1+Inputs!$B$7)^5+(Model!$F$5*($A6-B$3)/1000)*(1-Inputs!$B$5)/Inputs!$B$7/(1+Inputs!$B$7)^(5+(Inputs!$B$27-2031))-Inputs!$B$9-Inputs!$B$10-Inputs!$B$12*(1-Inputs!$B$5)/Inputs!$B$6-Inputs!$B$13)/Inputs!$B$4 -> 5.1666349 | C6: =(SUMPRODUCT(((Model!$B$6:$F$6+Model!$B$7:$F$7-C$3*Model!$B$5:$F$5/1000)*(1-Inputs!$B$5)+Inputs!$B$5*Model!$B$15:$F$15)*Model!$B$29:$F$29)+SUMPRODUCT((Model!$B$4:$F$4*Inputs!$B$36:$F$36/1000-C$3*Model!$B$4:$F$4/1000)*(1-Inputs!$B$5)*Model!$B$30:$F$30)-SUMPRODUCT(Model!$B$23:$F$23*Model!$B$29:$F$29)+((Model!$F$5*(Inputs!$B$23-C$3)/1000+MAX(0,Model!$F$5-Inputs!$B$24)*Inputs!$B$21/1000-Inputs!$B$25*Model!$F$5/Model!$F$3)*(1-Inputs!$B$5)+Inputs!$B$5*Inputs!$B$26)*(1-(1+Inputs!$B$6)^-(Inputs!$B$27-2031))/Inputs!$B$6/(1+Inputs!$B$6)^5+(Model!$F$4*($A6-C$3)/1000-Inputs!$B$25*(1-Model!$F$5/Model!$F$3))*(1-Inputs!$B$5)/Inputs!$B$7/(1+Inputs!$B$7)^5+(Model!$F$5*($A6-C$3)/1000)*(1-Inputs!$B$5)/Inputs!$B$7/(1+Inputs!$B$7)^(5+(Inputs!$B$27-2031))-Inputs!$B$9-Inputs!$B$10-Inputs!$B$12*(1-Inputs!$B$5)/Inputs!$B$6-Inputs!$B$13)/Inputs!$B$4 -> 8.5216331 | D6: =(SUMPRODUCT(((Model!$B$6:$F$6+Model!$B$7:$F$7-D$3*Model!$B$5:$F$5/1000)*(1-Inputs!$B$5)+Inputs!$B$5*Model!$B$15:$F$15)*Model!$B$29:$F$29)+SUMPRODUCT((Model!$B$4:$F$4*Inputs!$B$36:$F$36/1000-D$3*Model!$B$4:$F$4/1000)*(1-Inputs!$B$5)*Model!$B$30:$F$30)-SUMPRODUCT(Model!$B$23:$F$23*Model!$B$29:$F$29)+((Model!$F$5*(Inputs!$B$23-D$3)/1000+MAX(0,Model!$F$5-Inputs!$B$24)*Inputs!$B$21/1000-Inputs!$B$25*Model!$F$5/Model!$F$3)*(1-Inputs!$B$5)+Inputs!$B$5*Inputs!$B$26)*(1-(1+Inputs!$B$6)^-(Inputs!$B$27-2031))/Inputs!$B$6/(1+Inputs!$B$6)^5+(Model!$F$4*($A6-D$3)/1000-Inputs!$B$25*(1-Model!$F$5/Model!$F$3))*(1-Inputs!$B$5)/Inputs!$B$7/(1+Inputs!$B$7)^5+(Model!$F$5*($A6-D$3)/1000)*(1-Inputs!$B$5)/Inputs!$B$7/(1+Inputs!$B$7)^(5+(Inputs!$B$27-2031))-Inputs!$B$9-Inputs!$B$10-Inputs!$B$12*(1-Inputs!$B$5)/Inputs!$B$6-Inputs!$B$13)/Inputs!$B$4 -> 11.001414 | E6: =(SUMPRODUCT(((Model!$B$6:$F$6+Model!$B$7:$F$7-E$3*Model!$B$5:$F$5/1000)*(1-Inputs!$B$5)+Inputs!$B$5*Model!$B$15:$F$15)*Model!$B$29:$F$29)+SUMPRODUCT((Model!$B$4:$F$4*Inputs!$B$36:$F$36/1000-E$3*Model!$B$4:$F$4/1000)*(1-Inputs!$B$5)*Model!$B$30:$F$30)-SUMPRODUCT(Model!$B$23:$F$23*Model!$B$29:$F$29)+((Model!$F$5*(Inputs!$B$23-E$3)/1000+MAX(0,Model!$F$5-Inputs!$B$24)*Inputs!$B$21/1000-Inputs!$B$25*Model!$F$5/Model!$F$3)*(1-Inputs!$B$5)+Inputs!$B$5*Inputs!$B$26)*(1-(1+Inputs!$B$6)^-(Inputs!$B$27-2031))/Inputs!$B$6/(1+Inputs!$B$6)^5+(Model!$F$4*($A6-E$3)/1000-Inputs!$B$25*(1-Model!$F$5/Model!$F$3))*(1-Inputs!$B$5)/Inputs!$B$7/(1+Inputs!$B$7)^5+(Model!$F$5*($A6-E$3)/1000)*(1-Inputs!$B$5)/Inputs!$B$7/(1+Inputs!$B$7)^(5+(Inputs!$B$27-2031))-Inputs!$B$9-Inputs!$B$10-Inputs!$B$12*(1-Inputs!$B$5)/Inputs!$B$6-Inputs!$B$13)/Inputs!$B$4 -> 13.189457
A7: 4 | B7: =(SUMPRODUCT(((Model!$B$6:$F$6+Model!$B$7:$F$7-B$3*Model!$B$5:$F$5/1000)*(1-Inputs!$B$5)+Inputs!$B$5*Model!$B$15:$F$15)*Model!$B$29:$F$29)+SUMPRODUCT((Model!$B$4:$F$4*Inputs!$B$36:$F$36/1000-B$3*Model!$B$4:$F$4/1000)*(1-Inputs!$B$5)*Model!$B$30:$F$30)-SUMPRODUCT(Model!$B$23:$F$23*Model!$B$29:$F$29)+((Model!$F$5*(Inputs!$B$23-B$3)/1000+MAX(0,Model!$F$5-Inputs!$B$24)*Inputs!$B$21/1000-Inputs!$B$25*Model!$F$5/Model!$F$3)*(1-Inputs!$B$5)+Inputs!$B$5*Inputs!$B$26)*(1-(1+Inputs!$B$6)^-(Inputs!$B$27-2031))/Inputs!$B$6/(1+Inputs!$B$6)^5+(Model!$F$4*($A7-B$3)/1000-Inputs!$B$25*(1-Model!$F$5/Model!$F$3))*(1-Inputs!$B$5)/Inputs!$B$7/(1+Inputs!$B$7)^5+(Model!$F$5*($A7-B$3)/1000)*(1-Inputs!$B$5)/Inputs!$B$7/(1+Inputs!$B$7)^(5+(Inputs!$B$27-2031))-Inputs!$B$9-Inputs!$B$10-Inputs!$B$12*(1-Inputs!$B$5)/Inputs!$B$6-Inputs!$B$13)/Inputs!$B$4 -> 7.2215128 | C7: =(SUMPRODUCT(((Model!$B$6:$F$6+Model!$B$7:$F$7-C$3*Model!$B$5:$F$5/1000)*(1-Inputs!$B$5)+Inputs!$B$5*Model!$B$15:$F$15)*Model!$B$29:$F$29)+SUMPRODUCT((Model!$B$4:$F$4*Inputs!$B$36:$F$36/1000-C$3*Model!$B$4:$F$4/1000)*(1-Inputs!$B$5)*Model!$B$30:$F$30)-SUMPRODUCT(Model!$B$23:$F$23*Model!$B$29:$F$29)+((Model!$F$5*(Inputs!$B$23-C$3)/1000+MAX(0,Model!$F$5-Inputs!$B$24)*Inputs!$B$21/1000-Inputs!$B$25*Model!$F$5/Model!$F$3)*(1-Inputs!$B$5)+Inputs!$B$5*Inputs!$B$26)*(1-(1+Inputs!$B$6)^-(Inputs!$B$27-2031))/Inputs!$B$6/(1+Inputs!$B$6)^5+(Model!$F$4*($A7-C$3)/1000-Inputs!$B$25*(1-Model!$F$5/Model!$F$3))*(1-Inputs!$B$5)/Inputs!$B$7/(1+Inputs!$B$7)^5+(Model!$F$5*($A7-C$3)/1000)*(1-Inputs!$B$5)/Inputs!$B$7/(1+Inputs!$B$7)^(5+(Inputs!$B$27-2031))-Inputs!$B$9-Inputs!$B$10-Inputs!$B$12*(1-Inputs!$B$5)/Inputs!$B$6-Inputs!$B$13)/Inputs!$B$4 -> 10.576511 | D7: =(SUMPRODUCT(((Model!$B$6:$F$6+Model!$B$7:$F$7-D$3*Model!$B$5:$F$5/1000)*(1-Inputs!$B$5)+Inputs!$B$5*Model!$B$15:$F$15)*Model!$B$29:$F$29)+SUMPRODUCT((Model!$B$4:$F$4*Inputs!$B$36:$F$36/1000-D$3*Model!$B$4:$F$4/1000)*(1-Inputs!$B$5)*Model!$B$30:$F$30)-SUMPRODUCT(Model!$B$23:$F$23*Model!$B$29:$F$29)+((Model!$F$5*(Inputs!$B$23-D$3)/1000+MAX(0,Model!$F$5-Inputs!$B$24)*Inputs!$B$21/1000-Inputs!$B$25*Model!$F$5/Model!$F$3)*(1-Inputs!$B$5)+Inputs!$B$5*Inputs!$B$26)*(1-(1+Inputs!$B$6)^-(Inputs!$B$27-2031))/Inputs!$B$6/(1+Inputs!$B$6)^5+(Model!$F$4*($A7-D$3)/1000-Inputs!$B$25*(1-Model!$F$5/Model!$F$3))*(1-Inputs!$B$5)/Inputs!$B$7/(1+Inputs!$B$7)^5+(Model!$F$5*($A7-D$3)/1000)*(1-Inputs!$B$5)/Inputs!$B$7/(1+Inputs!$B$7)^(5+(Inputs!$B$27-2031))-Inputs!$B$9-Inputs!$B$10-Inputs!$B$12*(1-Inputs!$B$5)/Inputs!$B$6-Inputs!$B$13)/Inputs!$B$4 -> 13.056292 | E7: =(SUMPRODUCT(((Model!$B$6:$F$6+Model!$B$7:$F$7-E$3*Model!$B$5:$F$5/1000)*(1-Inputs!$B$5)+Inputs!$B$5*Model!$B$15:$F$15)*Model!$B$29:$F$29)+SUMPRODUCT((Model!$B$4:$F$4*Inputs!$B$36:$F$36/1000-E$3*Model!$B$4:$F$4/1000)*(1-Inputs!$B$5)*Model!$B$30:$F$30)-SUMPRODUCT(Model!$B$23:$F$23*Model!$B$29:$F$29)+((Model!$F$5*(Inputs!$B$23-E$3)/1000+MAX(0,Model!$F$5-Inputs!$B$24)*Inputs!$B$21/1000-Inputs!$B$25*Model!$F$5/Model!$F$3)*(1-Inputs!$B$5)+Inputs!$B$5*Inputs!$B$26)*(1-(1+Inputs!$B$6)^-(Inputs!$B$27-2031))/Inputs!$B$6/(1+Inputs!$B$6)^5+(Model!$F$4*($A7-E$3)/1000-Inputs!$B$25*(1-Model!$F$5/Model!$F$3))*(1-Inputs!$B$5)/Inputs!$B$7/(1+Inputs!$B$7)^5+(Model!$F$5*($A7-E$3)/1000)*(1-Inputs!$B$5)/Inputs!$B$7/(1+Inputs!$B$7)^(5+(Inputs!$B$27-2031))-Inputs!$B$9-Inputs!$B$10-Inputs!$B$12*(1-Inputs!$B$5)/Inputs!$B$6-Inputs!$B$13)/Inputs!$B$4 -> 15.244335
A8: 4.5 | B8: =(SUMPRODUCT(((Model!$B$6:$F$6+Model!$B$7:$F$7-B$3*Model!$B$5:$F$5/1000)*(1-Inputs!$B$5)+Inputs!$B$5*Model!$B$15:$F$15)*Model!$B$29:$F$29)+SUMPRODUCT((Model!$B$4:$F$4*Inputs!$B$36:$F$36/1000-B$3*Model!$B$4:$F$4/1000)*(1-Inputs!$B$5)*Model!$B$30:$F$30)-SUMPRODUCT(Model!$B$23:$F$23*Model!$B$29:$F$29)+((Model!$F$5*(Inputs!$B$23-B$3)/1000+MAX(0,Model!$F$5-Inputs!$B$24)*Inputs!$B$21/1000-Inputs!$B$25*Model!$F$5/Model!$F$3)*(1-Inputs!$B$5)+Inputs!$B$5*Inputs!$B$26)*(1-(1+Inputs!$B$6)^-(Inputs!$B$27-2031))/Inputs!$B$6/(1+Inputs!$B$6)^5+(Model!$F$4*($A8-B$3)/1000-Inputs!$B$25*(1-Model!$F$5/Model!$F$3))*(1-Inputs!$B$5)/Inputs!$B$7/(1+Inputs!$B$7)^5+(Model!$F$5*($A8-B$3)/1000)*(1-Inputs!$B$5)/Inputs!$B$7/(1+Inputs!$B$7)^(5+(Inputs!$B$27-2031))-Inputs!$B$9-Inputs!$B$10-Inputs!$B$12*(1-Inputs!$B$5)/Inputs!$B$6-Inputs!$B$13)/Inputs!$B$4 -> 9.2763906 | C8: =(SUMPRODUCT(((Model!$B$6:$F$6+Model!$B$7:$F$7-C$3*Model!$B$5:$F$5/1000)*(1-Inputs!$B$5)+Inputs!$B$5*Model!$B$15:$F$15)*Model!$B$29:$F$29)+SUMPRODUCT((Model!$B$4:$F$4*Inputs!$B$36:$F$36/1000-C$3*Model!$B$4:$F$4/1000)*(1-Inputs!$B$5)*Model!$B$30:$F$30)-SUMPRODUCT(Model!$B$23:$F$23*Model!$B$29:$F$29)+((Model!$F$5*(Inputs!$B$23-C$3)/1000+MAX(0,Model!$F$5-Inputs!$B$24)*Inputs!$B$21/1000-Inputs!$B$25*Model!$F$5/Model!$F$3)*(1-Inputs!$B$5)+Inputs!$B$5*Inputs!$B$26)*(1-(1+Inputs!$B$6)^-(Inputs!$B$27-2031))/Inputs!$B$6/(1+Inputs!$B$6)^5+(Model!$F$4*($A8-C$3)/1000-Inputs!$B$25*(1-Model!$F$5/Model!$F$3))*(1-Inputs!$B$5)/Inputs!$B$7/(1+Inputs!$B$7)^5+(Model!$F$5*($A8-C$3)/1000)*(1-Inputs!$B$5)/Inputs!$B$7/(1+Inputs!$B$7)^(5+(Inputs!$B$27-2031))-Inputs!$B$9-Inputs!$B$10-Inputs!$B$12*(1-Inputs!$B$5)/Inputs!$B$6-Inputs!$B$13)/Inputs!$B$4 -> 12.631389 | D8: =(SUMPRODUCT(((Model!$B$6:$F$6+Model!$B$7:$F$7-D$3*Model!$B$5:$F$5/1000)*(1-Inputs!$B$5)+Inputs!$B$5*Model!$B$15:$F$15)*Model!$B$29:$F$29)+SUMPRODUCT((Model!$B$4:$F$4*Inputs!$B$36:$F$36/1000-D$3*Model!$B$4:$F$4/1000)*(1-Inputs!$B$5)*Model!$B$30:$F$30)-SUMPRODUCT(Model!$B$23:$F$23*Model!$B$29:$F$29)+((Model!$F$5*(Inputs!$B$23-D$3)/1000+MAX(0,Model!$F$5-Inputs!$B$24)*Inputs!$B$21/1000-Inputs!$B$25*Model!$F$5/Model!$F$3)*(1-Inputs!$B$5)+Inputs!$B$5*Inputs!$B$26)*(1-(1+Inputs!$B$6)^-(Inputs!$B$27-2031))/Inputs!$B$6/(1+Inputs!$B$6)^5+(Model!$F$4*($A8-D$3)/1000-Inputs!$B$25*(1-Model!$F$5/Model!$F$3))*(1-Inputs!$B$5)/Inputs!$B$7/(1+Inputs!$B$7)^5+(Model!$F$5*($A8-D$3)/1000)*(1-Inputs!$B$5)/Inputs!$B$7/(1+Inputs!$B$7)^(5+(Inputs!$B$27-2031))-Inputs!$B$9-Inputs!$B$10-Inputs!$B$12*(1-Inputs!$B$5)/Inputs!$B$6-Inputs!$B$13)/Inputs!$B$4 -> 15.11117 | E8: =(SUMPRODUCT(((Model!$B$6:$F$6+Model!$B$7:$F$7-E$3*Model!$B$5:$F$5/1000)*(1-Inputs!$B$5)+Inputs!$B$5*Model!$B$15:$F$15)*Model!$B$29:$F$29)+SUMPRODUCT((Model!$B$4:$F$4*Inputs!$B$36:$F$36/1000-E$3*Model!$B$4:$F$4/1000)*(1-Inputs!$B$5)*Model!$B$30:$F$30)-SUMPRODUCT(Model!$B$23:$F$23*Model!$B$29:$F$29)+((Model!$F$5*(Inputs!$B$23-E$3)/1000+MAX(0,Model!$F$5-Inputs!$B$24)*Inputs!$B$21/1000-Inputs!$B$25*Model!$F$5/Model!$F$3)*(1-Inputs!$B$5)+Inputs!$B$5*Inputs!$B$26)*(1-(1+Inputs!$B$6)^-(Inputs!$B$27-2031))/Inputs!$B$6/(1+Inputs!$B$6)^5+(Model!$F$4*($A8-E$3)/1000-Inputs!$B$25*(1-Model!$F$5/Model!$F$3))*(1-Inputs!$B$5)/Inputs!$B$7/(1+Inputs!$B$7)^5+(Model!$F$5*($A8-E$3)/1000)*(1-Inputs!$B$5)/Inputs!$B$7/(1+Inputs!$B$7)^(5+(Inputs!$B$27-2031))-Inputs!$B$9-Inputs!$B$10-Inputs!$B$12*(1-Inputs!$B$5)/Inputs!$B$6-Inputs!$B$13)/Inputs!$B$4 -> 17.299213
A9: 5.19 | B9: =(SUMPRODUCT(((Model!$B$6:$F$6+Model!$B$7:$F$7-B$3*Model!$B$5:$F$5/1000)*(1-Inputs!$B$5)+Inputs!$B$5*Model!$B$15:$F$15)*Model!$B$29:$F$29)+SUMPRODUCT((Model!$B$4:$F$4*Inputs!$B$36:$F$36/1000-B$3*Model!$B$4:$F$4/1000)*(1-Inputs!$B$5)*Model!$B$30:$F$30)-SUMPRODUCT(Model!$B$23:$F$23*Model!$B$29:$F$29)+((Model!$F$5*(Inputs!$B$23-B$3)/1000+MAX(0,Model!$F$5-Inputs!$B$24)*Inputs!$B$21/1000-Inputs!$B$25*Model!$F$5/Model!$F$3)*(1-Inputs!$B$5)+Inputs!$B$5*Inputs!$B$26)*(1-(1+Inputs!$B$6)^-(Inputs!$B$27-2031))/Inputs!$B$6/(1+Inputs!$B$6)^5+(Model!$F$4*($A9-B$3)/1000-Inputs!$B$25*(1-Model!$F$5/Model!$F$3))*(1-Inputs!$B$5)/Inputs!$B$7/(1+Inputs!$B$7)^5+(Model!$F$5*($A9-B$3)/1000)*(1-Inputs!$B$5)/Inputs!$B$7/(1+Inputs!$B$7)^(5+(Inputs!$B$27-2031))-Inputs!$B$9-Inputs!$B$10-Inputs!$B$12*(1-Inputs!$B$5)/Inputs!$B$6-Inputs!$B$13)/Inputs!$B$4 -> 12.112122 | C9: =(SUMPRODUCT(((Model!$B$6:$F$6+Model!$B$7:$F$7-C$3*Model!$B$5:$F$5/1000)*(1-Inputs!$B$5)+Inputs!$B$5*Model!$B$15:$F$15)*Model!$B$29:$F$29)+SUMPRODUCT((Model!$B$4:$F$4*Inputs!$B$36:$F$36/1000-C$3*Model!$B$4:$F$4/1000)*(1-Inputs!$B$5)*Model!$B$30:$F$30)-SUMPRODUCT(Model!$B$23:$F$23*Model!$B$29:$F$29)+((Model!$F$5*(Inputs!$B$23-C$3)/1000+MAX(0,Model!$F$5-Inputs!$B$24)*Inputs!$B$21/1000-Inputs!$B$25*Model!$F$5/Model!$F$3)*(1-Inputs!$B$5)+Inputs!$B$5*Inputs!$B$26)*(1-(1+Inputs!$B$6)^-(Inputs!$B$27-2031))/Inputs!$B$6/(1+Inputs!$B$6)^5+(Model!$F$4*($A9-C$3)/1000-Inputs!$B$25*(1-Model!$F$5/Model!$F$3))*(1-Inputs!$B$5)/Inputs!$B$7/(1+Inputs!$B$7)^5+(Model!$F$5*($A9-C$3)/1000)*(1-Inputs!$B$5)/Inputs!$B$7/(1+Inputs!$B$7)^(5+(Inputs!$B$27-2031))-Inputs!$B$9-Inputs!$B$10-Inputs!$B$12*(1-Inputs!$B$5)/Inputs!$B$6-Inputs!$B$13)/Inputs!$B$4 -> 15.46712 | D9: =(SUMPRODUCT(((Model!$B$6:$F$6+Model!$B$7:$F$7-D$3*Model!$B$5:$F$5/1000)*(1-Inputs!$B$5)+Inputs!$B$5*Model!$B$15:$F$15)*Model!$B$29:$F$29)+SUMPRODUCT((Model!$B$4:$F$4*Inputs!$B$36:$F$36/1000-D$3*Model!$B$4:$F$4/1000)*(1-Inputs!$B$5)*Model!$B$30:$F$30)-SUMPRODUCT(Model!$B$23:$F$23*Model!$B$29:$F$29)+((Model!$F$5*(Inputs!$B$23-D$3)/1000+MAX(0,Model!$F$5-Inputs!$B$24)*Inputs!$B$21/1000-Inputs!$B$25*Model!$F$5/Model!$F$3)*(1-Inputs!$B$5)+Inputs!$B$5*Inputs!$B$26)*(1-(1+Inputs!$B$6)^-(Inputs!$B$27-2031))/Inputs!$B$6/(1+Inputs!$B$6)^5+(Model!$F$4*($A9-D$3)/1000-Inputs!$B$25*(1-Model!$F$5/Model!$F$3))*(1-Inputs!$B$5)/Inputs!$B$7/(1+Inputs!$B$7)^5+(Model!$F$5*($A9-D$3)/1000)*(1-Inputs!$B$5)/Inputs!$B$7/(1+Inputs!$B$7)^(5+(Inputs!$B$27-2031))-Inputs!$B$9-Inputs!$B$10-Inputs!$B$12*(1-Inputs!$B$5)/Inputs!$B$6-Inputs!$B$13)/Inputs!$B$4 -> 17.946902 | E9: =(SUMPRODUCT(((Model!$B$6:$F$6+Model!$B$7:$F$7-E$3*Model!$B$5:$F$5/1000)*(1-Inputs!$B$5)+Inputs!$B$5*Model!$B$15:$F$15)*Model!$B$29:$F$29)+SUMPRODUCT((Model!$B$4:$F$4*Inputs!$B$36:$F$36/1000-E$3*Model!$B$4:$F$4/1000)*(1-Inputs!$B$5)*Model!$B$30:$F$30)-SUMPRODUCT(Model!$B$23:$F$23*Model!$B$29:$F$29)+((Model!$F$5*(Inputs!$B$23-E$3)/1000+MAX(0,Model!$F$5-Inputs!$B$24)*Inputs!$B$21/1000-Inputs!$B$25*Model!$F$5/Model!$F$3)*(1-Inputs!$B$5)+Inputs!$B$5*Inputs!$B$26)*(1-(1+Inputs!$B$6)^-(Inputs!$B$27-2031))/Inputs!$B$6/(1+Inputs!$B$6)^5+(Model!$F$4*($A9-E$3)/1000-Inputs!$B$25*(1-Model!$F$5/Model!$F$3))*(1-Inputs!$B$5)/Inputs!$B$7/(1+Inputs!$B$7)^5+(Model!$F$5*($A9-E$3)/1000)*(1-Inputs!$B$5)/Inputs!$B$7/(1+Inputs!$B$7)^(5+(Inputs!$B$27-2031))-Inputs!$B$9-Inputs!$B$10-Inputs!$B$12*(1-Inputs!$B$5)/Inputs!$B$6-Inputs!$B$13)/Inputs!$B$4 -> 20.134944
A10: 6 | B10: =(SUMPRODUCT(((Model!$B$6:$F$6+Model!$B$7:$F$7-B$3*Model!$B$5:$F$5/1000)*(1-Inputs!$B$5)+Inputs!$B$5*Model!$B$15:$F$15)*Model!$B$29:$F$29)+SUMPRODUCT((Model!$B$4:$F$4*Inputs!$B$36:$F$36/1000-B$3*Model!$B$4:$F$4/1000)*(1-Inputs!$B$5)*Model!$B$30:$F$30)-SUMPRODUCT(Model!$B$23:$F$23*Model!$B$29:$F$29)+((Model!$F$5*(Inputs!$B$23-B$3)/1000+MAX(0,Model!$F$5-Inputs!$B$24)*Inputs!$B$21/1000-Inputs!$B$25*Model!$F$5/Model!$F$3)*(1-Inputs!$B$5)+Inputs!$B$5*Inputs!$B$26)*(1-(1+Inputs!$B$6)^-(Inputs!$B$27-2031))/Inputs!$B$6/(1+Inputs!$B$6)^5+(Model!$F$4*($A10-B$3)/1000-Inputs!$B$25*(1-Model!$F$5/Model!$F$3))*(1-Inputs!$B$5)/Inputs!$B$7/(1+Inputs!$B$7)^5+(Model!$F$5*($A10-B$3)/1000)*(1-Inputs!$B$5)/Inputs!$B$7/(1+Inputs!$B$7)^(5+(Inputs!$B$27-2031))-Inputs!$B$9-Inputs!$B$10-Inputs!$B$12*(1-Inputs!$B$5)/Inputs!$B$6-Inputs!$B$13)/Inputs!$B$4 -> 15.441024 | C10: =(SUMPRODUCT(((Model!$B$6:$F$6+Model!$B$7:$F$7-C$3*Model!$B$5:$F$5/1000)*(1-Inputs!$B$5)+Inputs!$B$5*Model!$B$15:$F$15)*Model!$B$29:$F$29)+SUMPRODUCT((Model!$B$4:$F$4*Inputs!$B$36:$F$36/1000-C$3*Model!$B$4:$F$4/1000)*(1-Inputs!$B$5)*Model!$B$30:$F$30)-SUMPRODUCT(Model!$B$23:$F$23*Model!$B$29:$F$29)+((Model!$F$5*(Inputs!$B$23-C$3)/1000+MAX(0,Model!$F$5-Inputs!$B$24)*Inputs!$B$21/1000-Inputs!$B$25*Model!$F$5/Model!$F$3)*(1-Inputs!$B$5)+Inputs!$B$5*Inputs!$B$26)*(1-(1+Inputs!$B$6)^-(Inputs!$B$27-2031))/Inputs!$B$6/(1+Inputs!$B$6)^5+(Model!$F$4*($A10-C$3)/1000-Inputs!$B$25*(1-Model!$F$5/Model!$F$3))*(1-Inputs!$B$5)/Inputs!$B$7/(1+Inputs!$B$7)^5+(Model!$F$5*($A10-C$3)/1000)*(1-Inputs!$B$5)/Inputs!$B$7/(1+Inputs!$B$7)^(5+(Inputs!$B$27-2031))-Inputs!$B$9-Inputs!$B$10-Inputs!$B$12*(1-Inputs!$B$5)/Inputs!$B$6-Inputs!$B$13)/Inputs!$B$4 -> 18.796023 | D10: =(SUMPRODUCT(((Model!$B$6:$F$6+Model!$B$7:$F$7-D$3*Model!$B$5:$F$5/1000)*(1-Inputs!$B$5)+Inputs!$B$5*Model!$B$15:$F$15)*Model!$B$29:$F$29)+SUMPRODUCT((Model!$B$4:$F$4*Inputs!$B$36:$F$36/1000-D$3*Model!$B$4:$F$4/1000)*(1-Inputs!$B$5)*Model!$B$30:$F$30)-SUMPRODUCT(Model!$B$23:$F$23*Model!$B$29:$F$29)+((Model!$F$5*(Inputs!$B$23-D$3)/1000+MAX(0,Model!$F$5-Inputs!$B$24)*Inputs!$B$21/1000-Inputs!$B$25*Model!$F$5/Model!$F$3)*(1-Inputs!$B$5)+Inputs!$B$5*Inputs!$B$26)*(1-(1+Inputs!$B$6)^-(Inputs!$B$27-2031))/Inputs!$B$6/(1+Inputs!$B$6)^5+(Model!$F$4*($A10-D$3)/1000-Inputs!$B$25*(1-Model!$F$5/Model!$F$3))*(1-Inputs!$B$5)/Inputs!$B$7/(1+Inputs!$B$7)^5+(Model!$F$5*($A10-D$3)/1000)*(1-Inputs!$B$5)/Inputs!$B$7/(1+Inputs!$B$7)^(5+(Inputs!$B$27-2031))-Inputs!$B$9-Inputs!$B$10-Inputs!$B$12*(1-Inputs!$B$5)/Inputs!$B$6-Inputs!$B$13)/Inputs!$B$4 -> 21.275804 | E10: =(SUMPRODUCT(((Model!$B$6:$F$6+Model!$B$7:$F$7-E$3*Model!$B$5:$F$5/1000)*(1-Inputs!$B$5)+Inputs!$B$5*Model!$B$15:$F$15)*Model!$B$29:$F$29)+SUMPRODUCT((Model!$B$4:$F$4*Inputs!$B$36:$F$36/1000-E$3*Model!$B$4:$F$4/1000)*(1-Inputs!$B$5)*Model!$B$30:$F$30)-SUMPRODUCT(Model!$B$23:$F$23*Model!$B$29:$F$29)+((Model!$F$5*(Inputs!$B$23-E$3)/1000+MAX(0,Model!$F$5-Inputs!$B$24)*Inputs!$B$21/1000-Inputs!$B$25*Model!$F$5/Model!$F$3)*(1-Inputs!$B$5)+Inputs!$B$5*Inputs!$B$26)*(1-(1+Inputs!$B$6)^-(Inputs!$B$27-2031))/Inputs!$B$6/(1+Inputs!$B$6)^5+(Model!$F$4*($A10-E$3)/1000-Inputs!$B$25*(1-Model!$F$5/Model!$F$3))*(1-Inputs!$B$5)/Inputs!$B$7/(1+Inputs!$B$7)^5+(Model!$F$5*($A10-E$3)/1000)*(1-Inputs!$B$5)/Inputs!$B$7/(1+Inputs!$B$7)^(5+(Inputs!$B$27-2031))-Inputs!$B$9-Inputs!$B$10-Inputs!$B$12*(1-Inputs!$B$5)/Inputs!$B$6-Inputs!$B$13)/Inputs!$B$4 -> 23.463846
