Workbook

Sheet Inputs
A1: Venture Global (VG) model v8 - inputs (blue = input, yellow = key assumption)
A3: Share price, Oct 7 2026 close ($) | B3: 13.05
A4: Diluted shares (bn) | B4: 2.643
A5: Tax rate | B5: 0.19
A6: Discount rate, contracted cash and capex | B6: 0.07
A7: Discount rate, open cargoes | B7: 0.1
A8: Cash interest rate on net debt | B8: 0.075246058
A9: P&L interest cost rate before capitalization | B9: 0.082336755
A10: Net debt end-2026 ($bn) | B10: 40.681
A11: Series A preferred liquidation ($bn) | B11: 3
A12: Preferred dividend ($bn/yr) | B12: 0.268
A13: Minority share of EBITDA ($bn/yr) | B13: 0.16
A14: BP adjustment ($bn) | B14: 1.4985
... A31: Contract run-off year | B31: 2049
A33: 2026 all-in cost per MMBtu (calibrated to guidance) | B33: =(Inputs!$B$16-Inputs!$B$17)*Inputs!$B$18/Inputs!$B$16+Inputs!$B$17*Inputs!$B$19/Inputs!$B$16-Inputs!$B$20*1000/Inputs!$B$16 -> 1.1474088
A34: Underlying cost per MMBtu ex basis | B34: =Inputs!$B$33-Inputs!$B$21*1000/Inputs!$B$16 -> 0.91643126
A36: Escalation tranches (weight, first escalation year)
A37: Calcasieu (MTPA) | B37: 10 | C37: 2027
A38: Plaquemines Phase 1 (MTPA) | B38: 13.3 | C38: 2028
A39: Plaquemines Phase 2 (MTPA) | B39: 6.7 | C39: 2029
A40: CP2 Phase 1 (weight) | B40: 0.5 | C40: 2031
A41: CP2 Phase 2 (weight) | B41: 0.5 | C41: 2032
A43: Annual inputs
A44: Item | B44: 2027 | C44: 2028 | D44: 2029 | E44: 2030 | F44: 2031
A45: Volume (TBtu) | B45: 2220 | C45: 3330 | D45: 4255 | E45: 4420 | F45: 4420
A46: Open volume (TBtu) | B46: 675 | C46: 1625 | D46: 2475 | E46: 1900 | F46: 1664
A47: CME futures fee, JKM method ($/MMBtu) | B47: 15.410171 | C47: 8.0345792 | D47: 5.1236417 | E47: 3.8009625 | F47: 2.5048958
A48: Contract fee before escalation ($/MMBtu) | B48: 3 | C48: 2.6 | D48: 2.45 | E48: 2.45 | F48: 2.45
A49: Plaquemines basis cost ($bn) | B49: 0.435 | C49: 0.2175 | D49: 0 | E49: 0 | F49: 0
A50: Committed capex ($bn) | B50: 10 | C50: 8 | D50: 5 | E50: 2 | F50: 1
A51: D&A ($bn) | B51: 1.25 | C51: 1.6 | D51: 2 | E51: 2.4 | F51: 2.6
A52: Capitalized interest ($bn) | B52: 1.4 | C52: 1.1 | D52: 0.6 | E52: 0.2 | F52: 0

Sheet Model
A1: Annual model, central case ($bn unless stated)
A2: Year | B2: 2027 | C2: 2028 | D2: 2029 | E2: 2030 | F2: 2031
A3: Volume (TBtu) | B3: =Inputs!B$45 -> 2220 | C3: =Inputs!C$45 -> 3330 | D3: =Inputs!D$45 -> 4255 | E3: =Inputs!E$45 -> 4420 | F3: =Inputs!F$45 -> 4420
A4: Open volume (TBtu) | B4: =Inputs!B$46 -> 675 | C4: =Inputs!C$46 -> 1625 | D4: =Inputs!D$46 -> 2475 | E4: =Inputs!E$46 -> 1900 | F4: =Inputs!F$46 -> 1664
A5: Contracted volume (TBtu) | B5: =B3-B4 -> 1545 | C5: =C3-C4 -> 1705 | D5: =D3-D4 -> 1780 | E5: =E3-E4 -> 2520 | F5: =F3-F4 -> 2756
A6: Escalation multiplier, base book | B6: =((Inputs!$B$37*(1+Inputs!$B$26*((1+Inputs!$B$27)^MAX(0,B$2-Inputs!$C$37+1)-1))+Inputs!$B$38*(1+Inputs!$B$26*((1+Inputs!$B$27)^MAX(0,B$2-Inputs!$C$38+1)-1))+Inputs!$B$39*(1+Inputs!$B$26*((1+Inputs!$B$27)^MAX(0,B$2-Inputs!$C$39+1)-1)))/(Inputs!$B$37+Inputs!$B$38+Inputs!$B$39)) -> 1.0014583 | C6: =((Inputs!$B$37*(1+Inputs!$B$26*((1+Inputs!$B$27)^MAX(0,C$2-Inputs!$C$37+1)-1))+Inputs!$B$38*(1+Inputs!$B$26*((1+Inputs!$B$27)^MAX(0,C$2-Inputs!$C$38+1)-1))+Inputs!$B$39*(1+Inputs!$B$26*((1+Inputs!$B$27)^MAX(0,C$2-Inputs!$C$39+1)-1)))/(Inputs!$B$37+Inputs!$B$38+Inputs!$B$39)) -> 1.0048927 | D6: =((Inputs!$B$37*(1+Inputs!$B$26*((1+Inputs!$B$27)^MAX(0,D$2-Inputs!$C$37+1)-1))+Inputs!$B$38*(1+Inputs!$B$26*((1+Inputs!$B$27)^MAX(0,D$2-Inputs!$C$38+1)-1))+Inputs!$B$39*(1+Inputs!$B$26*((1+Inputs!$B$27)^MAX(0,D$2-Inputs!$C$39+1)-1)))/(Inputs!$B$37+Inputs!$B$38+Inputs!$B$39)) -> 1.00939 | E6: =((Inputs!$B$37*(1+Inputs!$B$26*((1+Inputs!$B$27)^MAX(0,E$2-Inputs!$C$37+1)-1))+Inputs!$B$38*(1+Inputs!$B$26*((1+Inputs!$B$27)^MAX(0,E$2-Inputs!$C$38+1)-1))+Inputs!$B$39*(1+Inputs!$B$26*((1+Inputs!$B$27)^MAX(0,E$2-Inputs!$C$39+1)-1)))/(Inputs!$B$37+Inputs!$B$38+Inputs!$B$39)) -> 1.0139998 | F6: =((Inputs!$B$37*(1+Inputs!$B$26*((1+Inputs!$B$27)^MAX(0,F$2-Inputs!$C$37+1)-1))+Inputs!$B$38*(1+Inputs!$B$26*((1+Inputs!$B$27)^MAX(0,F$2-Inputs!$C$38+1)-1))+Inputs!$B$39*(1+Inputs!$B$26*((1+Inputs!$B$27)^MAX(0,F$2-Inputs!$C$39+1)-1)))/(Inputs!$B$37+Inputs!$B$38+Inputs!$B$39)) -> 1.0187248
A7: Escalation multiplier, CP2 | B7: =(Inputs!$B$40*(1+Inputs!$B$26*((1+Inputs!$B$27)^MAX(0,B$2-Inputs!$C$40+1)-1))+Inputs!$B$41*(1+Inputs!$B$26*((1+Inputs!$B$27)^MAX(0,B$2-Inputs!$C$41+1)-1))) -> 1 | C7: =(Inputs!$B$40*(1+Inputs!$B$26*((1+Inputs!$B$27)^MAX(0,C$2-Inputs!$C$40+1)-1))+Inputs!$B$41*(1+Inputs!$B$26*((1+Inputs!$B$27)^MAX(0,C$2-Inputs!$C$41+1)-1))) -> 1 | D7: =(Inputs!$B$40*(1+Inputs!$B$26*((1+Inputs!$B$27)^MAX(0,D$2-Inputs!$C$40+1)-1))+Inputs!$B$41*(1+Inputs!$B$26*((1+Inputs!$B$27)^MAX(0,D$2-Inputs!$C$41+1)-1))) -> 1 | E7: =(Inputs!$B$40*(1+Inputs!$B$26*((1+Inputs!$B$27)^MAX(0,E$2-Inputs!$C$40+1)-1))+Inputs!$B$41*(1+Inputs!$B$26*((1+Inputs!$B$27)^MAX(0,E$2-Inputs!$C$41+1)-1))) -> 1 | F7: =(Inputs!$B$40*(1+Inputs!$B$26*((1+Inputs!$B$27)^MAX(0,F$2-Inputs!$C$40+1)-1))+Inputs!$B$41*(1+Inputs!$B$26*((1+Inputs!$B$27)^MAX(0,F$2-Inputs!$C$41+1)-1))) -> 1.0021875
A8: Contracted margin before costs | B8: =(MIN(B5,Inputs!$B$25)*Inputs!B$48*B6+MAX(0,B5-Inputs!$B$25)*Inputs!B$48*IF(B$2>=2030,B7,1))/1000 -> 4.6417594 | C8: =(MIN(C5,Inputs!$B$25)*Inputs!C$48*C6+MAX(0,C5-Inputs!$B$25)*Inputs!C$48*IF(C$2>=2030,C7,1))/1000 -> 4.4528448 | D8: =(MIN(D5,Inputs!$B$25)*Inputs!D$48*D6+MAX(0,D5-Inputs!$B$25)*Inputs!D$48*IF(D$2>=2030,D7,1))/1000 -> 4.3968887 | E8: =(MIN(E5,Inputs!$B$25)*Inputs!E$48*E6+MAX(0,E5-Inputs!$B$25)*Inputs!E$48*IF(E$2>=2030,E7,1))/1000 -> 6.2275071 | F8: =(MIN(F5,Inputs!$B$25)*Inputs!F$48*F6+MAX(0,F5-Inputs!$B$25)*Inputs!F$48*IF(F$2>=2030,F7,1))/1000 -> 6.8301759
A9: CP2 contract premium | B9: =IF(B$2>=2030,MAX(0,B5-Inputs!$B$25)*Inputs!$B$22*B7/1000,0) -> 0 | C9: =IF(C$2>=2030,MAX(0,C5-Inputs!$B$25)*Inputs!$B$22*C7/1000,0) -> 0 | D9: =IF(D$2>=2030,MAX(0,D5-Inputs!$B$25)*Inputs!$B$22*D7/1000,0) -> 0 | E9: =IF(E$2>=2030,MAX(0,E5-Inputs!$B$25)*Inputs!$B$22*E7/1000,0) -> 0.384 | F9: =IF(F$2>=2030,MAX(0,F5-Inputs!$B$25)*Inputs!$B$22*F7/1000,0) -> 0.4794465
A10: Open margin before costs | B10: =B4*Inputs!B$47/1000 -> 10.401865 | C10: =C4*Inputs!C$47/1000 -> 13.056191 | D10: =D4*Inputs!D$47/1000 -> 12.681013 | E10: =E4*Inputs!E$47/1000 -> 7.2218288 | F10: =F4*Inputs!F$47/1000 -> 4.1681467
A11: Unit cost ($/MMBtu) | B11: =Inputs!$B$34*(1+Inputs!$B$28)^(B$2-2026) -> 0.91643126 | C11: =Inputs!$B$34*(1+Inputs!$B$28)^(C$2-2026) -> 0.91643126 | D11: =Inputs!$B$34*(1+Inputs!$B$28)^(D$2-2026) -> 0.91643126 | E11: =Inputs!$B$34*(1+Inputs!$B$28)^(E$2-2026) -> 0.91643126 | F11: =Inputs!$B$34*(1+Inputs!$B$28)^(F$2-2026) -> 0.91643126
A12: Operating cost | B12: =B11*B3/1000+Inputs!B$49 -> 2.4694774 | C12: =C11*C3/1000+Inputs!C$49 -> 3.2692161 | D12: =D11*D3/1000+Inputs!D$49 -> 3.899415 | E12: =E11*E3/1000+Inputs!E$49 -> 4.0506262 | F12: =F11*F3/1000+Inputs!F$49 -> 4.0506262
A13: EBITDA | B13: =B8+B9+B10-B12 -> 12.574147 | C13: =C8+C9+C10-C12 -> 14.23982 | D13: =D8+D9+D10-D12 -> 13.178487 | E13: =E8+E9+E10-E12 -> 9.7827097 | F13: =F8+F9+F10-F12 -> 7.4271429
A14: Cost on contracted volume | B14: =B12*B5/B3 -> 1.7186228 | C14: =C12*C5/C3 -> 1.6738779 | D14: =D12*D5/D3 -> 1.6312477 | E14: =E12*E5/E3 -> 2.3094068 | F14: =F12*F5/F3 -> 2.5256846
A15: Cost on open volume | B15: =B12*B4/B3 -> 0.75085462 | C15: =C12*C4/C3 -> 1.5953382 | D15: =D12*D4/D3 -> 2.2681674 | E15: =E12*E4/E3 -> 1.7412194 | F15: =F12*F4/F3 -> 1.5249416
A16: Contracted EBITDA | B16: =B8+B9-B14 -> 2.9231366 | C16: =C8+C9-C14 -> 2.7789669 | D16: =D8+D9-D14 -> 2.765641 | E16: =E8+E9-E14 -> 4.3021004 | F16: =F8+F9-F14 -> 4.7839378
A17: Open EBITDA | B17: =B10-B15 -> 9.6510107 | C17: =C10-C15 -> 11.460853 | D17: =D10-D15 -> 10.412846 | E17: =E10-E15 -> 5.4806093 | F17: =F10-F15 -> 2.643205
A18: D&A | B18: =Inputs!B$51 -> 1.25 | C18: =Inputs!C$51 -> 1.6 | D18: =Inputs!D$51 -> 2 | E18: =Inputs!E$51 -> 2.4 | F18: =Inputs!F$51 -> 2.6
A19: Cash interest on opening net debt | B19: =Inputs!$B$10*Inputs!$B$8 -> 3.0610849 | C19: =B31*Inputs!$B$8 -> 3.3017293 | D19: =C31*Inputs!$B$8 -> 3.296449 | E19: =D31*Inputs!$B$8 -> 3.1183588 | F19: =E31*Inputs!$B$8 -> 2.9006386
A20: Capitalized interest | B20: =Inputs!B$52 -> 1.4 | C20: =Inputs!C$52 -> 1.1 | D20: =Inputs!D$52 -> 0.6 | E20: =Inputs!E$52 -> 0.2 | F20: =Inputs!F$52 -> 0
A21: P&L interest after capitalization | B21: =Inputs!$B$10*Inputs!$B$9-B20 -> 1.9495415 | C21: =B31*Inputs!$B$9-C20 -> 2.5128627 | D21: =C31*Inputs!$B$9-D20 -> 3.0070848 | E21: =D31*Inputs!$B$9-E20 -> 3.2122126 | F21: =E31*Inputs!$B$9-F20 -> 3.1739758
A22: Pre-tax income | B22: =B13-B18-B21 -> 9.3746057 | C22: =C13-C18-C21 -> 10.126957 | D22: =D13-D18-D21 -> 8.171402 | E22: =E13-E18-E21 -> 4.1704971 | F22: =F13-F18-F21 -> 1.6531671
A23: Tax | B23: =Inputs!$B$5*MAX(0,B22) -> 1.7811751 | C23: =Inputs!$B$5*MAX(0,C22) -> 1.9241219 | D23: =Inputs!$B$5*MAX(0,D22) -> 1.5525664 | E23: =Inputs!$B$5*MAX(0,E22) -> 0.79239445 | F23: =Inputs!$B$5*MAX(0,F22) -> 0.31410174
A24: Preferred and minority | B24: =Inputs!$B$12+Inputs!$B$13 -> 0.428 | C24: =Inputs!$B$12+Inputs!$B$13 -> 0.428 | D24: =Inputs!$B$12+Inputs!$B$13 -> 0.428 | E24: =Inputs!$B$12+Inputs!$B$13 -> 0.428 | F24: =Inputs!$B$12+Inputs!$B$13 -> 0.428
A25: Net income to common | B25: =B22-B23-B24 -> 7.1654307 | C25: =C22-C23-C24 -> 7.7748353 | D25: =D22-D23-D24 -> 6.1908356 | E25: =E22-E23-E24 -> 2.9501027 | F25: =F22-F23-F24 -> 0.91106532
A26: EPS ($) | B26: =B25/Inputs!$B$4 -> 2.7110975 | C26: =C25/Inputs!$B$4 -> 2.9416706 | D26: =D25/Inputs!$B$4 -> 2.3423517 | E26: =E25/Inputs!$B$4 -> 1.1161947 | F26: =F25/Inputs!$B$4 -> 0.34470879
A27: Cash tax | B27: =Inputs!$B$5*MAX(0,B13-(B19-B20)-(1+0.3*0)) -> 1.8834819 | C27: =Inputs!$B$5*MAX(0,C13-(C19-C20)-(1+0.3*1)) -> 2.0402372 | D27: =Inputs!$B$5*MAX(0,D13-(D19-D20)-(1+0.3*2)) -> 1.6875872 | E27: =Inputs!$B$5*MAX(0,E13-(E19-E20)-(1+0.3*3)) -> 0.94322667 | F27: =Inputs!$B$5*MAX(0,F13-(F19-F20)-(1+0.3*4)) -> 0.44203582
A28: Capex | B28: =Inputs!B$50 -> 10 | C28: =Inputs!C$50 -> 8 | D28: =Inputs!D$50 -> 5 | E28: =Inputs!E$50 -> 2 | F28: =Inputs!F$50 -> 1
A29: Common dividend | B29: =Inputs!$B$15 -> 0.39968 | C29: =Inputs!$B$15 -> 0.39968 | D29: =Inputs!$B$15 -> 0.39968 | E29: =Inputs!$B$15 -> 0.39968 | F29: =Inputs!$B$15 -> 0.39968
A30: Free cash flow after dividends | B30: =B13-B19-B27-B28-B24-B29 -> -3.1980995 | C30: =C13-C19-C27-C28-C24-C29 -> 0.070173392 | D30: =D13-D19-D27-D28-D24-D29 -> 2.3667706 | E30: =E13-E19-E27-E28-E24-E29 -> 2.8934442 | F30: =F13-F19-F27-F28-F24-F29 -> 2.2567885
A31: Closing net debt | B31: =Inputs!$B$10-B30 -> 43.879099 | C31: =B31-C30 -> 43.808926 | D31: =C31-D30 -> 41.442155 | E31: =D31-E30 -> 38.548711 | F31: =E31-F30 -> 36.291923
A32: Net debt / EBITDA (x) | B32: =B31/B13 -> 3.4896282 | C32: =C31/C13 -> 3.0765084 | D32: =D31/D13 -> 3.1446824 | E32: =E31/E13 -> 3.9404942 | F32: =F31/F13 -> 4.8863908
A33: Discount factor, contracted | B33: =1/(1+Inputs!$B$6)^(B$2-2026) -> 0.93457944 | C33: =1/(1+Inputs!$B$6)^(C$2-2026) -> 0.87343873 | D33: =1/(1+Inputs!$B$6)^(D$2-2026) -> 0.81629788 | E33: =1/(1+Inputs!$B$6)^(E$2-2026) -> 0.76289521 | F33: =1/(1+Inputs!$B$6)^(F$2-2026) -> 0.71298618
A34: Discount factor, open | B34: =1/(1+Inputs!$B$7)^(B$2-2026) -> 0.90909091 | C34: =1/(1+Inputs!$B$7)^(C$2-2026) -> 0.82644628 | D34: =1/(1+Inputs!$B$7)^(D$2-2026) -> 0.7513148 | E34: =1/(1+Inputs!$B$7)^(E$2-2026) -> 0.68301346 | F34: =1/(1+Inputs!$B$7)^(F$2-2026) -> 0.62092132
A35: Discount factor from end-2028, contracted | B35: =IF(B$2>2028,1/(1+Inputs!$B$6)^(B$2-2028),0) -> 0 | C35: =IF(C$2>2028,1/(1+Inputs!$B$6)^(C$2-2028),0) -> 0 | D35: =IF(D$2>2028,1/(1+Inputs!$B$6)^(D$2-2028),0) -> 0.93457944 | E35: =IF(E$2>2028,1/(1+Inputs!$B$6)^(E$2-2028),0) -> 0.87343873 | F35: =IF(F$2>2028,1/(1+Inputs!$B$6)^(F$2-2028),0) -> 0.81629788
A36: Discount factor from end-2028, open | B36: =IF(B$2>2028,1/(1+Inputs!$B$7)^(B$2-2028),0) -> 0 | C36: =IF(C$2>2028,1/(1+Inputs!$B$7)^(C$2-2028),0) -> 0 | D36: =IF(D$2>2028,1/(1+Inputs!$B$7)^(D$2-2028),0) -> 0.90909091 | E36: =IF(E$2>2028,1/(1+Inputs!$B$7)^(E$2-2028),0) -> 0.82644628 | F36: =IF(F$2>2028,1/(1+Inputs!$B$7)^(F$2-2028),0) -> 0.7513148

Sheet Tail 2032-2049
A1: Contracted and open cash, 2032 to contract run-off, at 2031 volumes ($bn)
A2: Year | B2: Escalation, base book | C2: Escalation, CP2 | D2: Unit cost | E2: Contracted revenue | F2: Contracted EBITDA after maintenance | G2: Open EBITDA after maintenance | H2: DF contracted today | I2: DF open today | J2: DF contracted from end-2028 | K2: DF open from end-2028
A3: 2032 | B3: =((Inputs!$B$37*(1+Inputs!$B$26*((1+Inputs!$B$27)^MAX(0,$A3-Inputs!$C$37+1)-1))+Inputs!$B$38*(1+Inputs!$B$26*((1+Inputs!$B$27)^MAX(0,$A3-Inputs!$C$38+1)-1))+Inputs!$B$39*(1+Inputs!$B$26*((1+Inputs!$B$27)^MAX(0,$A3-Inputs!$C$39+1)-1)))/(Inputs!$B$37+Inputs!$B$38+Inputs!$B$39)) -> 1.0235679 | C3: =(Inputs!$B$40*(1+Inputs!$B$26*((1+Inputs!$B$27)^MAX(0,$A3-Inputs!$C$40+1)-1))+Inputs!$B$41*(1+Inputs!$B$26*((1+Inputs!$B$27)^MAX(0,$A3-Inputs!$C$41+1)-1))) -> 1.0066172 | D3: =Inputs!$B$34*(1+Inputs!$B$28)^($A3-2026) -> 0.91643126 | E3: =(MIN(Model!$F$5,Inputs!$B$25)*Inputs!$B$24*B3+MAX(0,Model!$F$5-Inputs!$B$25)*(Inputs!$B$24+Inputs!$B$22)*C3)/1000 -> 7.3432318 | F3: =E3-D3*Model!$F$5/1000-Inputs!$B$29*Model!$F$5/Model!$F$3 -> 4.1940178 | G3: =Model!$F$4*(Inputs!$B$23-D3)/1000-Inputs!$B$29*(1-Model!$F$5/Model!$F$3) -> 3.9225878 | H3: =1/(1+Inputs!$B$6)^($A3-2026) -> 0.66634222 | I3: =1/(1+Inputs!$B$7)^($A3-2026) -> 0.56447393 | J3: =1/(1+Inputs!$B$6)^($A3-2028) -> 0.76289521 | K3: =1/(1+Inputs!$B$7)^($A3-2028) -> 0.68301346
A4: 2033 | B4: =((Inputs!$B$37*(1+Inputs!$B$26*((1+Inputs!$B$27)^MAX(0,$A4-Inputs!$C$37+1)-1))+Inputs!$B$38*(1+Inputs!$B$26*((1+Inputs!$B$27)^MAX(0,$A4-Inputs!$C$38+1)-1))+Inputs!$B$39*(1+Inputs!$B$26*((1+Inputs!$B$27)^MAX(0,$A4-Inputs!$C$39+1)-1)))/(Inputs!$B$37+Inputs!$B$38+Inputs!$B$39)) -> 1.0285321 | C4: =(Inputs!$B$40*(1+Inputs!$B$26*((1+Inputs!$B$27)^MAX(0,$A4-Inputs!$C$40+1)-1))+Inputs!$B$41*(1+Inputs!$B$26*((1+Inputs!$B$27)^MAX(0,$A4-Inputs!$C$41+1)-1))) -> 1.0111576 | D4: =Inputs!$B$34*(1+Inputs!$B$28)^($A4-2026) -> 0.91643126 | E4: =(MIN(Model!$F$5,Inputs!$B$25)*Inputs!$B$24*B4+MAX(0,Model!$F$5-Inputs!$B$25)*(Inputs!$B$24+Inputs!$B$22)*C4)/1000 -> 7.3776815 | F4: =E4-D4*Model!$F$5/1000-Inputs!$B$29*Model!$F$5/Model!$F$3 -> 4.2284675 | G4: =Model!$F$4*(Inputs!$B$23-D4)/1000-Inputs!$B$29*(1-Model!$F$5/Model!$F$3) -> 3.9225878 | H4: =1/(1+Inputs!$B$6)^($A4-2026) -> 0.62274974 | I4: =1/(1+Inputs!$B$7)^($A4-2026) -> 0.51315812 | J4: =1/(1+Inputs!$B$6)^($A4-2028) -> 0.71298618 | K4: =1/(1+Inputs!$B$7)^($A4-2028) -> 0.62092132
A5: 2034 | B5: =((Inputs!$B$37*(1+Inputs!$B$26*((1+Inputs!$B$27)^MAX(0,$A5-Inputs!$C$37+1)-1))+Inputs!$B$38*(1+Inputs!$B$26*((1+Inputs!$B$27)^MAX(0,$A5-Inputs!$C$38+1)-1))+Inputs!$B$39*(1+Inputs!$B$26*((1+Inputs!$B$27)^MAX(0,$A5-Inputs!$C$39+1)-1)))/(Inputs!$B$37+Inputs!$B$38+Inputs!$B$39)) -> 1.0336204 | C5: =(Inputs!$B$40*(1+Inputs!$B$26*((1+Inputs!$B$27)^MAX(0,$A5-Inputs!$C$40+1)-1))+Inputs!$B$41*(1+Inputs!$B$26*((1+Inputs!$B$27)^MAX(0,$A5-Inputs!$C$41+1)-1))) -> 1.0158116 | D5: =Inputs!$B$34*(1+Inputs!$B$28)^($A5-2026) -> 0.91643126 | E5: =(MIN(Model!$F$5,Inputs!$B$25)*Inputs!$B$24*B5+MAX(0,Model!$F$5-Inputs!$B$25)*(Inputs!$B$24+Inputs!$B$22)*C5)/1000 -> 7.4129924 | F5: =E5-D5*Model!$F$5/1000-Inputs!$B$29*Model!$F$5/Model!$F$3 -> 4.2637784 | G5: =Model!$F$4*(Inputs!$B$23-D5)/1000-Inputs!$B$29*(1-Model!$F$5/Model!$F$3) -> 3.9225878 | H5: =1/(1+Inputs!$B$6)^($A5-2026) -> 0.5820091 | I5: =1/(1+Inputs!$B$7)^($A5-2026) -> 0.46650738 | J5: =1/(1+Inputs!$B$6)^($A5-2028) -> 0.66634222 | K5: =1/(1+Inputs!$B$7)^($A5-2028) -> 0.56447393
A6: 2035 | B6: =((Inputs!$B$37*(1+Inputs!$B$26*((1+Inputs!$B$27)^MAX(0,$A6-Inputs!$C$37+1)-1))+Inputs!$B$38*(1+Inputs!$B$26*((1+Inputs!$B$27)^MAX(0,$A6-Inputs!$C$38+1)-1))+Inputs!$B$39*(1+Inputs!$B$26*((1+Inputs!$B$27)^MAX(0,$A6-Inputs!$C$39+1)-1)))/(Inputs!$B$37+Inputs!$B$38+Inputs!$B$39)) -> 1.0388359 | C6: =(Inputs!$B$40*(1+Inputs!$B$26*((1+Inputs!$B$27)^MAX(0,$A6-Inputs!$C$40+1)-1))+Inputs!$B$41*(1+Inputs!$B$26*((1+Inputs!$B$27)^MAX(0,$A6-Inputs!$C$41+1)-1))) -> 1.0205818 | D6: =Inputs!$B$34*(1+Inputs!$B$28)^($A6-2026) -> 0.91643126 | E6: =(MIN(Model!$F$5,Inputs!$B$25)*Inputs!$B$24*B6+MAX(0,Model!$F$5-Inputs!$B$25)*(Inputs!$B$24+Inputs!$B$22)*C6)/1000 -> 7.4491861 | F6: =E6-D6*Model!$F$5/1000-Inputs!$B$29*Model!$F$5/Model!$F$3 -> 4.2999721 | G6: =Model!$F$4*(Inputs!$B$23-D6)/1000-Inputs!$B$29*(1-Model!$F$5/Model!$F$3) -> 3.9225878 | H6: =1/(1+Inputs!$B$6)^($A6-2026) -> 0.54393374 | I6: =1/(1+Inputs!$B$7)^($A6-2026) -> 0.42409762 | J6: =1/(1+Inputs!$B$6)^($A6-2028) -> 0.62274974 | K6: =1/(1+Inputs!$B$7)^($A6-2028) -> 0.51315812
A7: 2036 | B7: =((Inputs!$B$37*(1+Inputs!$B$26*((1+Inputs!$B$27)^MAX(0,$A7-Inputs!$C$37+1)-1))+Inputs!$B$38*(1+Inputs!$B$26*((1+Inputs!$B$27)^MAX(0,$A7-Inputs!$C$38+1)-1))+Inputs!$B$39*(1+Inputs!$B$26*((1+Inputs!$B$27)^MAX(0,$A7-Inputs!$C$39+1)-1)))/(Inputs!$B$37+Inputs!$B$38+Inputs!$B$39)) -> 1.0441818 | C7: =(Inputs!$B$40*(1+Inputs!$B$26*((1+Inputs!$B$27)^MAX(0,$A7-Inputs!$C$40+1)-1))+Inputs!$B$41*(1+Inputs!$B$26*((1+Inputs!$B$27)^MAX(0,$A7-Inputs!$C$41+1)-1))) -> 1.0254714 | D7: =Inputs!$B$34*(1+Inputs!$B$28)^($A7-2026) -> 0.91643126 | E7: =(MIN(Model!$F$5,Inputs!$B$25)*Inputs!$B$24*B7+MAX(0,Model!$F$5-Inputs!$B$25)*(Inputs!$B$24+Inputs!$B$22)*C7)/1000 -> 7.4862846 | F7: =E7-D7*Model!$F$5/1000-Inputs!$B$29*Model!$F$5/Model!$F$3 -> 4.3370706 | G7: =Model!$F$4*(Inputs!$B$23-D7)/1000-Inputs!$B$29*(1-Model!$F$5/Model!$F$3) -> 3.9225878 | H7: =1/(1+Inputs!$B$6)^($A7-2026) -> 0.50834929 | I7: =1/(1+Inputs!$B$7)^($A7-2026) -> 0.38554329 | J7: =1/(1+Inputs!$B$6)^($A7-2028) -> 0.5820091 | K7: =1/(1+Inputs!$B$7)^($A7-2028) -> 0.46650738
A8: 2037 | B8: =((Inputs!$B$37*(1+Inputs!$B$26*((1+Inputs!$B$27)^MAX(0,$A8-Inputs!$C$37+1)-1))+Inputs!$B$38*(1+Inputs!$B$26*((1+Inputs!$B$27)^MAX(0,$A8-Inputs!$C$38+1)-1))+Inputs!$B$39*(1+Inputs!$B$26*((1+Inputs!$B$27)^MAX(0,$A8-Inputs!$C$39+1)-1)))/(Inputs!$B$37+Inputs!$B$38+Inputs!$B$39)) -> 1.0496613 | C8: =(Inputs!$B$40*(1+Inputs!$B$26*((1+Inputs!$B$27)^MAX(0,$A8-Inputs!$C$40+1)-1))+Inputs!$B$41*(1+Inputs!$B$26*((1+Inputs!$B$27)^MAX(0,$A8-Inputs!$C$41+1)-1))) -> 1.0304832 | D8: =Inputs!$B$34*(1+Inputs!$B$28)^($A8-2026) -> 0.91643126 | E8: =(MIN(Model!$F$5,Inputs!$B$25)*Inputs!$B$24*B8+MAX(0,Model!$F$5-Inputs!$B$25)*(Inputs!$B$24+Inputs!$B$22)*C8)/1000 -> 7.5243106 | F8: =E8-D8*Model!$F$5/1000-Inputs!$B$29*Model!$F$5/Model!$F$3 -> 4.3750966 | G8: =Model!$F$4*(Inputs!$B$23-D8)/1000-Inputs!$B$29*(1-Model!$F$5/Model!$F$3) -> 3.9225878 | H8: =1/(1+Inputs!$B$6)^($A8-2026) -> 0.4750928 | I8: =1/(1+Inputs!$B$7)^($A8-2026) -> 0.3504939 | J8: =1/(1+Inputs!$B$6)^($A8-2028) -> 0.54393374 | K8: =1/(1+Inputs!$B$7)^($A8-2028) -> 0.42409762
A9: 2038 | B9: =((Inputs!$B$37*(1+Inputs!$B$26*((1+Inputs!$B$27)^MAX(0,$A9-Inputs!$C$37+1)-1))+Inputs!$B$38*(1+Inputs!$B$26*((1+Inputs!$B$27)^MAX(0,$A9-Inputs!$C$38+1)-1))+Inputs!$B$39*(1+Inputs!$B$26*((1+Inputs!$B$27)^MAX(0,$A9-Inputs!$C$39+1)-1)))/(Inputs!$B$37+Inputs!$B$38+Inputs!$B$39)) -> 1.0552779 | C9: =(Inputs!$B$40*(1+Inputs!$B$26*((1+Inputs!$B$27)^MAX(0,$A9-Inputs!$C$40+1)-1))+Inputs!$B$41*(1+Inputs!$B$26*((1+Inputs!$B$27)^MAX(0,$A9-Inputs!$C$41+1)-1))) -> 1.0356203 | D9: =Inputs!$B$34*(1+Inputs!$B$28)^($A9-2026) -> 0.91643126 | E9: =(MIN(Model!$F$5,Inputs!$B$25)*Inputs!$B$24*B9+MAX(0,Model!$F$5-Inputs!$B$25)*(Inputs!$B$24+Inputs!$B$22)*C9)/1000 -> 7.5632872 | F9: =E9-D9*Model!$F$5/1000-Inputs!$B$29*Model!$F$5/Model!$F$3 -> 4.4140733 | G9: =Model!$F$4*(Inputs!$B$23-D9)/1000-Inputs!$B$29*(1-Model!$F$5/Model!$F$3) -> 3.9225878 | H9: =1/(1+Inputs!$B$6)^($A9-2026) -> 0.44401196 | I9: =1/(1+Inputs!$B$7)^($A9-2026) -> 0.31863082 | J9: =1/(1+Inputs!$B$6)^($A9-2028) -> 0.50834929 | K9: =1/(1+Inputs!$B$7)^($A9-2028) -> 0.38554329
A10: 2039 | B10: =((Inputs!$B$37*(1+Inputs!$B$26*((1+Inputs!$B$27)^MAX(0,$A10-Inputs!$C$37+1)-1))+Inputs!$B$38*(1+Inputs!$B$26*((1+Inputs!$B$27)^MAX(0,$A10-Inputs!$C$38+1)-1))+Inputs!$B$39*(1+Inputs!$B$26*((1+Inputs!$B$27)^MAX(0,$A10-Inputs!$C$39+1)-1)))/(Inputs!$B$37+Inputs!$B$38+Inputs!$B$39)) -> 1.0610348 | C10: =(Inputs!$B$40*(1+Inputs!$B$26*((1+Inputs!$B$27)^MAX(0,$A10-Inputs!$C$40+1)-1))+Inputs!$B$41*(1+Inputs!$B$26*((1+Inputs!$B$27)^MAX(0,$A10-Inputs!$C$41+1)-1))) -> 1.0408858 | D10: =Inputs!$B$34*(1+Inputs!$B$28)^($A10-2026) -> 0.91643126 | E10: =(MIN(Model!$F$5,Inputs!$B$25)*Inputs!$B$24*B10+MAX(0,Model!$F$5-Inputs!$B$25)*(Inputs!$B$24+Inputs!$B$22)*C10)/1000 -> 7.6032383 | F10: =E10-D10*Model!$F$5/1000-Inputs!$B$29*Model!$F$5/Model!$F$3 -> 4.4540243 | G10: =Model!$F$4*(Inputs!$B$23-D10)/1000-Inputs!$B$29*(1-Model!$F$5/Model!$F$3) -> 3.9225878 | H10: =1/(1+Inputs!$B$6)^($A10-2026) -> 0.41496445 | I10: =1/(1+Inputs!$B$7)^($A10-2026) -> 0.28966438 | J10: =1/(1+Inputs!$B$6)^($A10-2028) -> 0.4750928 | K10: =1/(1+Inputs!$B$7)^($A10-2028) -> 0.3504939
A11: 2040 | B11: =((Inputs!$B$37*(1+Inputs!$B$26*((1+Inputs!$B$27)^MAX(0,$A11-Inputs!$C$37+1)-1))+Inputs!$B$38*(1+Inputs!$B$26*((1+Inputs!$B$27)^MAX(0,$A11-Inputs!$C$38+1)-1))+Inputs!$B$39*(1+Inputs!$B$26*((1+Inputs!$B$27)^MAX(0,$A11-Inputs!$C$39+1)-1)))/(Inputs!$B$37+Inputs!$B$38+Inputs!$B$39)) -> 1.0669357 | C11: =(Inputs!$B$40*(1+Inputs!$B$26*((1+Inputs!$B$27)^MAX(0,$A11-Inputs!$C$40+1)-1))+Inputs!$B$41*(1+Inputs!$B$26*((1+Inputs!$B$27)^MAX(0,$A11-Inputs!$C$41+1)-1))) -> 1.0462829 | D11: =Inputs!$B$34*(1+Inputs!$B$28)^($A11-2026) -> 0.91643126 | E11: =(MIN(Model!$F$5,Inputs!$B$25)*Inputs!$B$24*B11+MAX(0,Model!$F$5-Inputs!$B$25)*(Inputs!$B$24+Inputs!$B$22)*C11)/1000 -> 7.6441881 | F11: =E11-D11*Model!$F$5/1000-Inputs!$B$29*Model!$F$5/Model!$F$3 -> 4.4949742 | G11: =Model!$F$4*(Inputs!$B$23-D11)/1000-Inputs!$B$29*(1-Model!$F$5/Model!$F$3) -> 3.9225878 | H11: =1/(1+Inputs!$B$6)^($A11-2026) -> 0.38781724 | I11: =1/(1+Inputs!$B$7)^($A11-2026) -> 0.26333125 | J11: =1/(1+Inputs!$B$6)^($A11-2028) -> 0.44401196 | K11: =1/(1+Inputs!$B$7)^($A11-2028) -> 0.31863082
A12: 2041 | B12: =((Inputs!$B$37*(1+Inputs!$B$26*((1+Inputs!$B$27)^MAX(0,$A12-Inputs!$C$37+1)-1))+Inputs!$B$38*(1+Inputs!$B$26*((1+Inputs!$B$27)^MAX(0,$A12-Inputs!$C$38+1)-1))+Inputs!$B$39*(1+Inputs!$B$26*((1+Inputs!$B$27)^MAX(0,$A12-Inputs!$C$39+1)-1)))/(Inputs!$B$37+Inputs!$B$38+Inputs!$B$39)) -> 1.0729841 | C12: =(Inputs!$B$40*(1+Inputs!$B$26*((1+Inputs!$B$27)^MAX(0,$A12-Inputs!$C$40+1)-1))+Inputs!$B$41*(1+Inputs!$B$26*((1+Inputs!$B$27)^MAX(0,$A12-Inputs!$C$41+1)-1))) -> 1.051815 | D12: =Inputs!$B$34*(1+Inputs!$B$28)^($A12-2026) -> 0.91643126 | E12: =(MIN(Model!$F$5,Inputs!$B$25)*Inputs!$B$24*B12+MAX(0,Model!$F$5-Inputs!$B$25)*(Inputs!$B$24+Inputs!$B$22)*C12)/1000 -> 7.6861617 | F12: =E12-D12*Model!$F$5/1000-Inputs!$B$29*Model!$F$5/Model!$F$3 -> 4.5369477 | G12: =Model!$F$4*(Inputs!$B$23-D12)/1000-Inputs!$B$29*(1-Model!$F$5/Model!$F$3) -> 3.9225878 | H12: =1/(1+Inputs!$B$6)^($A12-2026) -> 0.36244602 | I12: =1/(1+Inputs!$B$7)^($A12-2026) -> 0.23939205 | J12: =1/(1+Inputs!$B$6)^($A12-2028) -> 0.41496445 | K12: =1/(1+Inputs!$B$7)^($A12-2028) -> 0.28966438
A13: 2042 | B13: =((Inputs!$B$37*(1+Inputs!$B$26*((1+Inputs!$B$27)^MAX(0,$A13-Inputs!$C$37+1)-1))+Inputs!$B$38*(1+Inputs!$B$26*((1+Inputs!$B$27)^MAX(0,$A13-Inputs!$C$38+1)-1))+Inputs!$B$39*(1+Inputs!$B$26*((1+Inputs!$B$27)^MAX(0,$A13-Inputs!$C$39+1)-1)))/(Inputs!$B$37+Inputs!$B$38+Inputs!$B$39)) -> 1.0791837 | C13: =(Inputs!$B$40*(1+Inputs!$B$26*((1+Inputs!$B$27)^MAX(0,$A13-Inputs!$C$40+1)-1))+Inputs!$B$41*(1+Inputs!$B$26*((1+Inputs!$B$27)^MAX(0,$A13-Inputs!$C$41+1)-1))) -> 1.0574854 | D13: =Inputs!$B$34*(1+Inputs!$B$28)^($A13-2026) -> 0.91643126 | E13: =(MIN(Model!$F$5,Inputs!$B$25)*Inputs!$B$24*B13+MAX(0,Model!$F$5-Inputs!$B$25)*(Inputs!$B$24+Inputs!$B$22)*C13)/1000 -> 7.7291846 | F13: =E13-D13*Model!$F$5/1000-Inputs!$B$29*Model!$F$5/Model!$F$3 -> 4.5799707 | G13: =Model!$F$4*(Inputs!$B$23-D13)/1000-Inputs!$B$29*(1-Model!$F$5/Model!$F$3) -> 3.9225878 | H13: =1/(1+Inputs!$B$6)^($A13-2026) -> 0.3387346 | I13: =1/(1+Inputs!$B$7)^($A13-2026) -> 0.21762914 | J13: =1/(1+Inputs!$B$6)^($A13-2028) -> 0.38781724 | K13: =1/(1+Inputs!$B$7)^($A13-2028) -> 0.26333125
A14: 2043 | B14: =((Inputs!$B$37*(1+Inputs!$B$26*((1+Inputs!$B$27)^MAX(0,$A14-Inputs!$C$37+1)-1))+Inputs!$B$38*(1+Inputs!$B$26*((1+Inputs!$B$27)^MAX(0,$A14-Inputs!$C$38+1)-1))+Inputs!$B$39*(1+Inputs!$B$26*((1+Inputs!$B$27)^MAX(0,$A14-Inputs!$C$39+1)-1)))/(Inputs!$B$37+Inputs!$B$38+Inputs!$B$39)) -> 1.0855383 | C14: =(Inputs!$B$40*(1+Inputs!$B$26*((1+Inputs!$B$27)^MAX(0,$A14-Inputs!$C$40+1)-1))+Inputs!$B$41*(1+Inputs!$B$26*((1+Inputs!$B$27)^MAX(0,$A14-Inputs!$C$41+1)-1))) -> 1.0632975 | D14: =Inputs!$B$34*(1+Inputs!$B$28)^($A14-2026) -> 0.91643126 | E14: =(MIN(Model!$F$5,Inputs!$B$25)*Inputs!$B$24*B14+MAX(0,Model!$F$5-Inputs!$B$25)*(Inputs!$B$24+Inputs!$B$22)*C14)/1000 -> 7.7732831 | F14: =E14-D14*Model!$F$5/1000-Inputs!$B$29*Model!$F$5/Model!$F$3 -> 4.6240691 | G14: =Model!$F$4*(Inputs!$B$23-D14)/1000-Inputs!$B$29*(1-Model!$F$5/Model!$F$3) -> 3.9225878 | H14: =1/(1+Inputs!$B$6)^($A14-2026) -> 0.31657439 | I14: =1/(1+Inputs!$B$7)^($A14-2026) -> 0.19784467 | J14: =1/(1+Inputs!$B$6)^($A14-2028) -> 0.36244602 | K14: =1/(1+Inputs!$B$7)^($A14-2028) -> 0.23939205
... A20: 2049 | B20: =((Inputs!$B$37*(1+Inputs!$B$26*((1+Inputs!$B$27)^MAX(0,$A20-Inputs!$C$37+1)-1))+Inputs!$B$38*(1+Inputs!$B$26*((1+Inputs!$B$27)^MAX(0,$A20-Inputs!$C$38+1)-1))+Inputs!$B$39*(1+Inputs!$B$26*((1+Inputs!$B$27)^MAX(0,$A20-Inputs!$C$39+1)-1)))/(Inputs!$B$37+Inputs!$B$38+Inputs!$B$39)) -> 1.1271445 | C20: =(Inputs!$B$40*(1+Inputs!$B$26*((1+Inputs!$B$27)^MAX(0,$A20-Inputs!$C$40+1)-1))+Inputs!$B$41*(1+Inputs!$B$26*((1+Inputs!$B$27)^MAX(0,$A20-Inputs!$C$41+1)-1))) -> 1.101352 | D20: =Inputs!$B$34*(1+Inputs!$B$28)^($A20-2026) -> 0.91643126 | E20: =(MIN(Model!$F$5,Inputs!$B$25)*Inputs!$B$24*B20+MAX(0,Model!$F$5-Inputs!$B$25)*(Inputs!$B$24+Inputs!$B$22)*C20)/1000 -> 8.0620149 | F20: =E20-D20*Model!$F$5/1000-Inputs!$B$29*Model!$F$5/Model!$F$3 -> 4.9128009 | G20: =Model!$F$4*(Inputs!$B$23-D20)/1000-Inputs!$B$29*(1-Model!$F$5/Model!$F$3) -> 3.9225878 | H20: =1/(1+Inputs!$B$6)^($A20-2026) -> 0.21094688 | I20: =1/(1+Inputs!$B$7)^($A20-2026) -> 0.11167816 | J20: =1/(1+Inputs!$B$6)^($A20-2028) -> 0.24151309 | K20: =1/(1+Inputs!$B$7)^($A20-2028) -> 0.13513057

Sheet Valuation
A1: Sum of the parts ($bn unless stated)
A3: PV contracted cash 2027-31 | B3: =SUMPRODUCT((Model!$B$16:$F$16*(1-Inputs!$B$5)+Inputs!$B$5*Model!$B$18:$F$18)*Model!$B$33:$F$33) -> 12.926618
A4: PV open cargoes 2027-31 | B4: =SUMPRODUCT(Model!$B$17:$F$17*(1-Inputs!$B$5)*Model!$B$34:$F$34) -> 25.477175
A5: PV committed capex | B5: =-SUMPRODUCT(Model!$B$28:$F$28*Model!$B$33:$F$33) -> -22.65357
A6: PV contracted cash 2032-2049 (escalating) | B6: =SUMPRODUCT(('Tail 2032-2049'!$F$3:$F$20*(1-Inputs!$B$5)+Inputs!$B$5*Inputs!$B$30)*'Tail 2032-2049'!$H$3:$H$20) -> 29.42634
A7: PV open cargoes 2032-2049 | B7: =SUMPRODUCT('Tail 2032-2049'!$G$3:$G$20*(1-Inputs!$B$5)*'Tail 2032-2049'!$I$3:$I$20) -> 16.180163
A8: PV all volume as open after 2049 | B8: =((Model!$F$4*(Inputs!$B$23-'Tail 2032-2049'!$D$20)/1000-Inputs!$B$29*(1-Model!$F$5/Model!$F$3))+Model!$F$5*(Inputs!$B$23-'Tail 2032-2049'!$D$20)/1000)*(1-Inputs!$B$5)/Inputs!$B$7/(1+Inputs!$B$7)^(Inputs!$B$31-2026) -> 9.9893338
A9: Less net debt end-2026 | B9: =-Inputs!$B$10 -> -40.681
A10: Less preferred | B10: =-Inputs!$B$11 -> -3
A11: Less Calcasieu minority | B11: =-Inputs!$B$13*(1-Inputs!$B$5)/Inputs!$B$6 -> -1.8514286
A12: Less BP adjustment | B12: =-Inputs!$B$14 -> -1.4985
A13: Equity value today | B13: =SUM(B3:B12) -> 24.315132
A14: Value per share today ($) | B14: =B13/Inputs!$B$4 -> 9.1998228
A15: Value at end-2028
A16: PV contracted cash 2029-31 | B16: =SUMPRODUCT((Model!$B$16:$F$16*(1-Inputs!$B$5)+Inputs!$B$5*Model!$B$18:$F$18)*Model!$B$35:$F$35) -> 9.4571144
A17: PV open cargoes 2029-31 | B17: =SUMPRODUCT(Model!$B$17:$F$17*(1-Inputs!$B$5)*Model!$B$36:$F$36) -> 12.945041
A18: PV capex 2029-31 | B18: =-SUMPRODUCT(Model!$B$28:$F$28*Model!$B$35:$F$35) -> -7.2360725
A19: PV contracted cash 2032-2049 | B19: =SUMPRODUCT(('Tail 2032-2049'!$F$3:$F$20*(1-Inputs!$B$5)+Inputs!$B$5*Inputs!$B$30)*'Tail 2032-2049'!$J$3:$J$20) -> 33.690217
A20: PV open cargoes 2032-2049 | B20: =SUMPRODUCT('Tail 2032-2049'!$G$3:$G$20*(1-Inputs!$B$5)*'Tail 2032-2049'!$K$3:$K$20) -> 19.577998
A21: PV all volume as open after 2049 | B21: =((Model!$F$4*(Inputs!$B$23-'Tail 2032-2049'!$D$20)/1000-Inputs!$B$29*(1-Model!$F$5/Model!$F$3))+Model!$F$5*(Inputs!$B$23-'Tail 2032-2049'!$D$20)/1000)*(1-Inputs!$B$5)/Inputs!$B$7/(1+Inputs!$B$7)^(Inputs!$B$31-2028) -> 12.087094
A22: Less net debt end-2028 | B22: =-Model!$C$31 -> -43.808926
A23: Less preferred | B23: =-Inputs!$B$11 -> -3
A24: Less Calcasieu minority | B24: =-Inputs!$B$13*(1-Inputs!$B$5)/Inputs!$B$6 -> -1.8514286
A25: Less BP adjustment | B25: =-Inputs!$B$14 -> -1.4985
A26: Value per share at end-2028 ($) = 24-month target | B26: =SUM(B16:B25)/Inputs!$B$4 -> 11.487906
A27: Implied equity return a year, incl. dividends | B27: =((B26+2*0.16)/B14)^(1/2.23)-1 -> 0.11842514
A28: Share price ($) | B28: =Inputs!$B$3 -> 13.05
A29: Value per share per $1 of long-run fee | B29: =((Model!$F$4/1000)*(1-Inputs!$B$5)*SUM('Tail 2032-2049'!$I$3:$I$20)+((Model!$F$4+Model!$F$5)/1000)*(1-Inputs!$B$5)/Inputs!$B$7/(1+Inputs!$B$7)^(Inputs!$B$31-2026))/Inputs!$B$4 -> 4.1097558
A30: Long-run fee the price needs ($/MMBtu) | B30: =Inputs!$B$23+(B28-B14)/B29 -> 4.4368384

Sheet Grid
A1: Value per share today: long-run fee from 2032 (rows) x flat cost per MMBtu (columns), no basis cost, escalation on
A3: Long-run fee \ cost | B3: 1.15 | C3: 0.92 | D3: 0.75 | E3: 0.6
A4: 2.5 | B4: =(SUMPRODUCT(((Model!$B$8:$F$8+Model!$B$9:$F$9-B$3*Model!$B$5:$F$5/1000)*(1-Inputs!$B$5)+Inputs!$B$5*Model!$B$18:$F$18)*Model!$B$33:$F$33)+SUMPRODUCT((Model!$B$4:$F$4*Inputs!$B$47:$F$47/1000-B$3*Model!$B$4:$F$4/1000)*(1-Inputs!$B$5)*Model!$B$34:$F$34)-SUMPRODUCT(Model!$B$28:$F$28*Model!$B$33:$F$33)+SUMPRODUCT((('Tail 2032-2049'!$E$3:$E$20-B$3*Model!$F$5/1000-Inputs!$B$29*Model!$F$5/Model!$F$3)*(1-Inputs!$B$5)+Inputs!$B$5*Inputs!$B$30)*'Tail 2032-2049'!$H$3:$H$20)+(Model!$F$4*($A4-B$3)/1000-Inputs!$B$29*(1-Model!$F$5/Model!$F$3))*(1-Inputs!$B$5)*SUM('Tail 2032-2049'!$I$3:$I$20)+((Model!$F$4*($A4-B$3)/1000-Inputs!$B$29*(1-Model!$F$5/Model!$F$3))+Model!$F$5*($A4-B$3)/1000)*(1-Inputs!$B$5)/Inputs!$B$7/(1+Inputs!$B$7)^(Inputs!$B$31-2026)-Inputs!$B$10-Inputs!$B$11-Inputs!$B$13*(1-Inputs!$B$5)/Inputs!$B$6-Inputs!$B$14)/Inputs!$B$4 -> 1.863264 | C4: =(SUMPRODUCT(((Model!$B$8:$F$8+Model!$B$9:$F$9-C$3*Model!$B$5:$F$5/1000)*(1-Inputs!$B$5)+Inputs!$B$5*Model!$B$18:$F$18)*Model!$B$33:$F$33)+SUMPRODUCT((Model!$B$4:$F$4*Inputs!$B$47:$F$47/1000-C$3*Model!$B$4:$F$4/1000)*(1-Inputs!$B$5)*Model!$B$34:$F$34)-SUMPRODUCT(Model!$B$28:$F$28*Model!$B$33:$F$33)+SUMPRODUCT((('Tail 2032-2049'!$E$3:$E$20-C$3*Model!$F$5/1000-Inputs!$B$29*Model!$F$5/Model!$F$3)*(1-Inputs!$B$5)+Inputs!$B$5*Inputs!$B$30)*'Tail 2032-2049'!$H$3:$H$20)+(Model!$F$4*($A4-C$3)/1000-Inputs!$B$29*(1-Model!$F$5/Model!$F$3))*(1-Inputs!$B$5)*SUM('Tail 2032-2049'!$I$3:$I$20)+((Model!$F$4*($A4-C$3)/1000-Inputs!$B$29*(1-Model!$F$5/Model!$F$3))+Model!$F$5*($A4-C$3)/1000)*(1-Inputs!$B$5)/Inputs!$B$7/(1+Inputs!$B$7)^(Inputs!$B$31-2026)-Inputs!$B$10-Inputs!$B$11-Inputs!$B$13*(1-Inputs!$B$5)/Inputs!$B$6-Inputs!$B$14)/Inputs!$B$4 -> 5.2182622 | D4: =(SUMPRODUCT(((Model!$B$8:$F$8+Model!$B$9:$F$9-D$3*Model!$B$5:$F$5/1000)*(1-Inputs!$B$5)+Inputs!$B$5*Model!$B$18:$F$18)*Model!$B$33:$F$33)+SUMPRODUCT((Model!$B$4:$F$4*Inputs!$B$47:$F$47/1000-D$3*Model!$B$4:$F$4/1000)*(1-Inputs!$B$5)*Model!$B$34:$F$34)-SUMPRODUCT(Model!$B$28:$F$28*Model!$B$33:$F$33)+SUMPRODUCT((('Tail 2032-2049'!$E$3:$E$20-D$3*Model!$F$5/1000-Inputs!$B$29*Model!$F$5/Model!$F$3)*(1-Inputs!$B$5)+Inputs!$B$5*Inputs!$B$30)*'Tail 2032-2049'!$H$3:$H$20)+(Model!$F$4*($A4-D$3)/1000-Inputs!$B$29*(1-Model!$F$5/Model!$F$3))*(1-Inputs!$B$5)*SUM('Tail 2032-2049'!$I$3:$I$20)+((Model!$F$4*($A4-D$3)/1000-Inputs!$B$29*(1-Model!$F$5/Model!$F$3))+Model!$F$5*($A4-D$3)/1000)*(1-Inputs!$B$5)/Inputs!$B$7/(1+Inputs!$B$7)^(Inputs!$B$31-2026)-Inputs!$B$10-Inputs!$B$11-Inputs!$B$13*(1-Inputs!$B$5)/Inputs!$B$6-Inputs!$B$14)/Inputs!$B$4 -> 7.6980435 | E4: =(SUMPRODUCT(((Model!$B$8:$F$8+Model!$B$9:$F$9-E$3*Model!$B$5:$F$5/1000)*(1-Inputs!$B$5)+Inputs!$B$5*Model!$B$18:$F$18)*Model!$B$33:$F$33)+SUMPRODUCT((Model!$B$4:$F$4*Inputs!$B$47:$F$47/1000-E$3*Model!$B$4:$F$4/1000)*(1-Inputs!$B$5)*Model!$B$34:$F$34)-SUMPRODUCT(Model!$B$28:$F$28*Model!$B$33:$F$33)+SUMPRODUCT((('Tail 2032-2049'!$E$3:$E$20-E$3*Model!$F$5/1000-Inputs!$B$29*Model!$F$5/Model!$F$3)*(1-Inputs!$B$5)+Inputs!$B$5*Inputs!$B$30)*'Tail 2032-2049'!$H$3:$H$20)+(Model!$F$4*($A4-E$3)/1000-Inputs!$B$29*(1-Model!$F$5/Model!$F$3))*(1-Inputs!$B$5)*SUM('Tail 2032-2049'!$I$3:$I$20)+((Model!$F$4*($A4-E$3)/1000-Inputs!$B$29*(1-Model!$F$5/Model!$F$3))+Model!$F$5*($A4-E$3)/1000)*(1-Inputs!$B$5)/Inputs!$B$7/(1+Inputs!$B$7)^(Inputs!$B$31-2026)-Inputs!$B$10-Inputs!$B$11-Inputs!$B$13*(1-Inputs!$B$5)/Inputs!$B$6-Inputs!$B$14)/Inputs!$B$4 -> 9.8860858
A5: 3 | B5: =(SUMPRODUCT(((Model!$B$8:$F$8+Model!$B$9:$F$9-B$3*Model!$B$5:$F$5/1000)*(1-Inputs!$B$5)+Inputs!$B$5*Model!$B$18:$F$18)*Model!$B$33:$F$33)+SUMPRODUCT((Model!$B$4:$F$4*Inputs!$B$47:$F$47/1000-B$3*Model!$B$4:$F$4/1000)*(1-Inputs!$B$5)*Model!$B$34:$F$34)-SUMPRODUCT(Model!$B$28:$F$28*Model!$B$33:$F$33)+SUMPRODUCT((('Tail 2032-2049'!$E$3:$E$20-B$3*Model!$F$5/1000-Inputs!$B$29*Model!$F$5/Model!$F$3)*(1-Inputs!$B$5)+Inputs!$B$5*Inputs!$B$30)*'Tail 2032-2049'!$H$3:$H$20)+(Model!$F$4*($A5-B$3)/1000-Inputs!$B$29*(1-Model!$F$5/Model!$F$3))*(1-Inputs!$B$5)*SUM('Tail 2032-2049'!$I$3:$I$20)+((Model!$F$4*($A5-B$3)/1000-Inputs!$B$29*(1-Model!$F$5/Model!$F$3))+Model!$F$5*($A5-B$3)/1000)*(1-Inputs!$B$5)/Inputs!$B$7/(1+Inputs!$B$7)^(Inputs!$B$31-2026)-Inputs!$B$10-Inputs!$B$11-Inputs!$B$13*(1-Inputs!$B$5)/Inputs!$B$6-Inputs!$B$14)/Inputs!$B$4 -> 3.9181419 | C5: =(SUMPRODUCT(((Model!$B$8:$F$8+Model!$B$9:$F$9-C$3*Model!$B$5:$F$5/1000)*(1-Inputs!$B$5)+Inputs!$B$5*Model!$B$18:$F$18)*Model!$B$33:$F$33)+SUMPRODUCT((Model!$B$4:$F$4*Inputs!$B$47:$F$47/1000-C$3*Model!$B$4:$F$4/1000)*(1-Inputs!$B$5)*Model!$B$34:$F$34)-SUMPRODUCT(Model!$B$28:$F$28*Model!$B$33:$F$33)+SUMPRODUCT((('Tail 2032-2049'!$E$3:$E$20-C$3*Model!$F$5/1000-Inputs!$B$29*Model!$F$5/Model!$F$3)*(1-Inputs!$B$5)+Inputs!$B$5*Inputs!$B$30)*'Tail 2032-2049'!$H$3:$H$20)+(Model!$F$4*($A5-C$3)/1000-Inputs!$B$29*(1-Model!$F$5/Model!$F$3))*(1-Inputs!$B$5)*SUM('Tail 2032-2049'!$I$3:$I$20)+((Model!$F$4*($A5-C$3)/1000-Inputs!$B$29*(1-Model!$F$5/Model!$F$3))+Model!$F$5*($A5-C$3)/1000)*(1-Inputs!$B$5)/Inputs!$B$7/(1+Inputs!$B$7)^(Inputs!$B$31-2026)-Inputs!$B$10-Inputs!$B$11-Inputs!$B$13*(1-Inputs!$B$5)/Inputs!$B$6-Inputs!$B$14)/Inputs!$B$4 -> 7.2731401 | D5: =(SUMPRODUCT(((Model!$B$8:$F$8+Model!$B$9:$F$9-D$3*Model!$B$5:$F$5/1000)*(1-Inputs!$B$5)+Inputs!$B$5*Model!$B$18:$F$18)*Model!$B$33:$F$33)+SUMPRODUCT((Model!$B$4:$F$4*Inputs!$B$47:$F$47/1000-D$3*Model!$B$4:$F$4/1000)*(1-Inputs!$B$5)*Model!$B$34:$F$34)-SUMPRODUCT(Model!$B$28:$F$28*Model!$B$33:$F$33)+SUMPRODUCT((('Tail 2032-2049'!$E$3:$E$20-D$3*Model!$F$5/1000-Inputs!$B$29*Model!$F$5/Model!$F$3)*(1-Inputs!$B$5)+Inputs!$B$5*Inputs!$B$30)*'Tail 2032-2049'!$H$3:$H$20)+(Model!$F$4*($A5-D$3)/1000-Inputs!$B$29*(1-Model!$F$5/Model!$F$3))*(1-Inputs!$B$5)*SUM('Tail 2032-2049'!$I$3:$I$20)+((Model!$F$4*($A5-D$3)/1000-Inputs!$B$29*(1-Model!$F$5/Model!$F$3))+Model!$F$5*($A5-D$3)/1000)*(1-Inputs!$B$5)/Inputs!$B$7/(1+Inputs!$B$7)^(Inputs!$B$31-2026)-Inputs!$B$10-Inputs!$B$11-Inputs!$B$13*(1-Inputs!$B$5)/Inputs!$B$6-Inputs!$B$14)/Inputs!$B$4 -> 9.7529214 | E5: =(SUMPRODUCT(((Model!$B$8:$F$8+Model!$B$9:$F$9-E$3*Model!$B$5:$F$5/1000)*(1-Inputs!$B$5)+Inputs!$B$5*Model!$B$18:$F$18)*Model!$B$33:$F$33)+SUMPRODUCT((Model!$B$4:$F$4*Inputs!$B$47:$F$47/1000-E$3*Model!$B$4:$F$4/1000)*(1-Inputs!$B$5)*Model!$B$34:$F$34)-SUMPRODUCT(Model!$B$28:$F$28*Model!$B$33:$F$33)+SUMPRODUCT((('Tail 2032-2049'!$E$3:$E$20-E$3*Model!$F$5/1000-Inputs!$B$29*Model!$F$5/Model!$F$3)*(1-Inputs!$B$5)+Inputs!$B$5*Inputs!$B$30)*'Tail 2032-2049'!$H$3:$H$20)+(Model!$F$4*($A5-E$3)/1000-Inputs!$B$29*(1-Model!$F$5/Model!$F$3))*(1-Inputs!$B$5)*SUM('Tail 2032-2049'!$I$3:$I$20)+((Model!$F$4*($A5-E$3)/1000-Inputs!$B$29*(1-Model!$F$5/Model!$F$3))+Model!$F$5*($A5-E$3)/1000)*(1-Inputs!$B$5)/Inputs!$B$7/(1+Inputs!$B$7)^(Inputs!$B$31-2026)-Inputs!$B$10-Inputs!$B$11-Inputs!$B$13*(1-Inputs!$B$5)/Inputs!$B$6-Inputs!$B$14)/Inputs!$B$4 -> 11.940964
A6: 3.5 | B6: =(SUMPRODUCT(((Model!$B$8:$F$8+Model!$B$9:$F$9-B$3*Model!$B$5:$F$5/1000)*(1-Inputs!$B$5)+Inputs!$B$5*Model!$B$18:$F$18)*Model!$B$33:$F$33)+SUMPRODUCT((Model!$B$4:$F$4*Inputs!$B$47:$F$47/1000-B$3*Model!$B$4:$F$4/1000)*(1-Inputs!$B$5)*Model!$B$34:$F$34)-SUMPRODUCT(Model!$B$28:$F$28*Model!$B$33:$F$33)+SUMPRODUCT((('Tail 2032-2049'!$E$3:$E$20-B$3*Model!$F$5/1000-Inputs!$B$29*Model!$F$5/Model!$F$3)*(1-Inputs!$B$5)+Inputs!$B$5*Inputs!$B$30)*'Tail 2032-2049'!$H$3:$H$20)+(Model!$F$4*($A6-B$3)/1000-Inputs!$B$29*(1-Model!$F$5/Model!$F$3))*(1-Inputs!$B$5)*SUM('Tail 2032-2049'!$I$3:$I$20)+((Model!$F$4*($A6-B$3)/1000-Inputs!$B$29*(1-Model!$F$5/Model!$F$3))+Model!$F$5*($A6-B$3)/1000)*(1-Inputs!$B$5)/Inputs!$B$7/(1+Inputs!$B$7)^(Inputs!$B$31-2026)-Inputs!$B$10-Inputs!$B$11-Inputs!$B$13*(1-Inputs!$B$5)/Inputs!$B$6-Inputs!$B$14)/Inputs!$B$4 -> 5.9730197 | C6: =(SUMPRODUCT(((Model!$B$8:$F$8+Model!$B$9:$F$9-C$3*Model!$B$5:$F$5/1000)*(1-Inputs!$B$5)+Inputs!$B$5*Model!$B$18:$F$18)*Model!$B$33:$F$33)+SUMPRODUCT((Model!$B$4:$F$4*Inputs!$B$47:$F$47/1000-C$3*Model!$B$4:$F$4/1000)*(1-Inputs!$B$5)*Model!$B$34:$F$34)-SUMPRODUCT(Model!$B$28:$F$28*Model!$B$33:$F$33)+SUMPRODUCT((('Tail 2032-2049'!$E$3:$E$20-C$3*Model!$F$5/1000-Inputs!$B$29*Model!$F$5/Model!$F$3)*(1-Inputs!$B$5)+Inputs!$B$5*Inputs!$B$30)*'Tail 2032-2049'!$H$3:$H$20)+(Model!$F$4*($A6-C$3)/1000-Inputs!$B$29*(1-Model!$F$5/Model!$F$3))*(1-Inputs!$B$5)*SUM('Tail 2032-2049'!$I$3:$I$20)+((Model!$F$4*($A6-C$3)/1000-Inputs!$B$29*(1-Model!$F$5/Model!$F$3))+Model!$F$5*($A6-C$3)/1000)*(1-Inputs!$B$5)/Inputs!$B$7/(1+Inputs!$B$7)^(Inputs!$B$31-2026)-Inputs!$B$10-Inputs!$B$11-Inputs!$B$13*(1-Inputs!$B$5)/Inputs!$B$6-Inputs!$B$14)/Inputs!$B$4 -> 9.328018 | D6: =(SUMPRODUCT(((Model!$B$8:$F$8+Model!$B$9:$F$9-D$3*Model!$B$5:$F$5/1000)*(1-Inputs!$B$5)+Inputs!$B$5*Model!$B$18:$F$18)*Model!$B$33:$F$33)+SUMPRODUCT((Model!$B$4:$F$4*Inputs!$B$47:$F$47/1000-D$3*Model!$B$4:$F$4/1000)*(1-Inputs!$B$5)*Model!$B$34:$F$34)-SUMPRODUCT(Model!$B$28:$F$28*Model!$B$33:$F$33)+SUMPRODUCT((('Tail 2032-2049'!$E$3:$E$20-D$3*Model!$F$5/1000-Inputs!$B$29*Model!$F$5/Model!$F$3)*(1-Inputs!$B$5)+Inputs!$B$5*Inputs!$B$30)*'Tail 2032-2049'!$H$3:$H$20)+(Model!$F$4*($A6-D$3)/1000-Inputs!$B$29*(1-Model!$F$5/Model!$F$3))*(1-Inputs!$B$5)*SUM('Tail 2032-2049'!$I$3:$I$20)+((Model!$F$4*($A6-D$3)/1000-Inputs!$B$29*(1-Model!$F$5/Model!$F$3))+Model!$F$5*($A6-D$3)/1000)*(1-Inputs!$B$5)/Inputs!$B$7/(1+Inputs!$B$7)^(Inputs!$B$31-2026)-Inputs!$B$10-Inputs!$B$11-Inputs!$B$13*(1-Inputs!$B$5)/Inputs!$B$6-Inputs!$B$14)/Inputs!$B$4 -> 11.807799 | E6: =(SUMPRODUCT(((Model!$B$8:$F$8+Model!$B$9:$F$9-E$3*Model!$B$5:$F$5/1000)*(1-Inputs!$B$5)+Inputs!$B$5*Model!$B$18:$F$18)*Model!$B$33:$F$33)+SUMPRODUCT((Model!$B$4:$F$4*Inputs!$B$47:$F$47/1000-E$3*Model!$B$4:$F$4/1000)*(1-Inputs!$B$5)*Model!$B$34:$F$34)-SUMPRODUCT(Model!$B$28:$F$28*Model!$B$33:$F$33)+SUMPRODUCT((('Tail 2032-2049'!$E$3:$E$20-E$3*Model!$F$5/1000-Inputs!$B$29*Model!$F$5/Model!$F$3)*(1-Inputs!$B$5)+Inputs!$B$5*Inputs!$B$30)*'Tail 2032-2049'!$H$3:$H$20)+(Model!$F$4*($A6-E$3)/1000-Inputs!$B$29*(1-Model!$F$5/Model!$F$3))*(1-Inputs!$B$5)*SUM('Tail 2032-2049'!$I$3:$I$20)+((Model!$F$4*($A6-E$3)/1000-Inputs!$B$29*(1-Model!$F$5/Model!$F$3))+Model!$F$5*($A6-E$3)/1000)*(1-Inputs!$B$5)/Inputs!$B$7/(1+Inputs!$B$7)^(Inputs!$B$31-2026)-Inputs!$B$10-Inputs!$B$11-Inputs!$B$13*(1-Inputs!$B$5)/Inputs!$B$6-Inputs!$B$14)/Inputs!$B$4 -> 13.995842
A7: 4 | B7: =(SUMPRODUCT(((Model!$B$8:$F$8+Model!$B$9:$F$9-B$3*Model!$B$5:$F$5/1000)*(1-Inputs!$B$5)+Inputs!$B$5*Model!$B$18:$F$18)*Model!$B$33:$F$33)+SUMPRODUCT((Model!$B$4:$F$4*Inputs!$B$47:$F$47/1000-B$3*Model!$B$4:$F$4/1000)*(1-Inputs!$B$5)*Model!$B$34:$F$34)-SUMPRODUCT(Model!$B$28:$F$28*Model!$B$33:$F$33)+SUMPRODUCT((('Tail 2032-2049'!$E$3:$E$20-B$3*Model!$F$5/1000-Inputs!$B$29*Model!$F$5/Model!$F$3)*(1-Inputs!$B$5)+Inputs!$B$5*Inputs!$B$30)*'Tail 2032-2049'!$H$3:$H$20)+(Model!$F$4*($A7-B$3)/1000-Inputs!$B$29*(1-Model!$F$5/Model!$F$3))*(1-Inputs!$B$5)*SUM('Tail 2032-2049'!$I$3:$I$20)+((Model!$F$4*($A7-B$3)/1000-Inputs!$B$29*(1-Model!$F$5/Model!$F$3))+Model!$F$5*($A7-B$3)/1000)*(1-Inputs!$B$5)/Inputs!$B$7/(1+Inputs!$B$7)^(Inputs!$B$31-2026)-Inputs!$B$10-Inputs!$B$11-Inputs!$B$13*(1-Inputs!$B$5)/Inputs!$B$6-Inputs!$B$14)/Inputs!$B$4 -> 8.0278976 | C7: =(SUMPRODUCT(((Model!$B$8:$F$8+Model!$B$9:$F$9-C$3*Model!$B$5:$F$5/1000)*(1-Inputs!$B$5)+Inputs!$B$5*Model!$B$18:$F$18)*Model!$B$33:$F$33)+SUMPRODUCT((Model!$B$4:$F$4*Inputs!$B$47:$F$47/1000-C$3*Model!$B$4:$F$4/1000)*(1-Inputs!$B$5)*Model!$B$34:$F$34)-SUMPRODUCT(Model!$B$28:$F$28*Model!$B$33:$F$33)+SUMPRODUCT((('Tail 2032-2049'!$E$3:$E$20-C$3*Model!$F$5/1000-Inputs!$B$29*Model!$F$5/Model!$F$3)*(1-Inputs!$B$5)+Inputs!$B$5*Inputs!$B$30)*'Tail 2032-2049'!$H$3:$H$20)+(Model!$F$4*($A7-C$3)/1000-Inputs!$B$29*(1-Model!$F$5/Model!$F$3))*(1-Inputs!$B$5)*SUM('Tail 2032-2049'!$I$3:$I$20)+((Model!$F$4*($A7-C$3)/1000-Inputs!$B$29*(1-Model!$F$5/Model!$F$3))+Model!$F$5*($A7-C$3)/1000)*(1-Inputs!$B$5)/Inputs!$B$7/(1+Inputs!$B$7)^(Inputs!$B$31-2026)-Inputs!$B$10-Inputs!$B$11-Inputs!$B$13*(1-Inputs!$B$5)/Inputs!$B$6-Inputs!$B$14)/Inputs!$B$4 -> 11.382896 | D7: =(SUMPRODUCT(((Model!$B$8:$F$8+Model!$B$9:$F$9-D$3*Model!$B$5:$F$5/1000)*(1-Inputs!$B$5)+Inputs!$B$5*Model!$B$18:$F$18)*Model!$B$33:$F$33)+SUMPRODUCT((Model!$B$4:$F$4*Inputs!$B$47:$F$47/1000-D$3*Model!$B$4:$F$4/1000)*(1-Inputs!$B$5)*Model!$B$34:$F$34)-SUMPRODUCT(Model!$B$28:$F$28*Model!$B$33:$F$33)+SUMPRODUCT((('Tail 2032-2049'!$E$3:$E$20-D$3*Model!$F$5/1000-Inputs!$B$29*Model!$F$5/Model!$F$3)*(1-Inputs!$B$5)+Inputs!$B$5*Inputs!$B$30)*'Tail 2032-2049'!$H$3:$H$20)+(Model!$F$4*($A7-D$3)/1000-Inputs!$B$29*(1-Model!$F$5/Model!$F$3))*(1-Inputs!$B$5)*SUM('Tail 2032-2049'!$I$3:$I$20)+((Model!$F$4*($A7-D$3)/1000-Inputs!$B$29*(1-Model!$F$5/Model!$F$3))+Model!$F$5*($A7-D$3)/1000)*(1-Inputs!$B$5)/Inputs!$B$7/(1+Inputs!$B$7)^(Inputs!$B$31-2026)-Inputs!$B$10-Inputs!$B$11-Inputs!$B$13*(1-Inputs!$B$5)/Inputs!$B$6-Inputs!$B$14)/Inputs!$B$4 -> 13.862677 | E7: =(SUMPRODUCT(((Model!$B$8:$F$8+Model!$B$9:$F$9-E$3*Model!$B$5:$F$5/1000)*(1-Inputs!$B$5)+Inputs!$B$5*Model!$B$18:$F$18)*Model!$B$33:$F$33)+SUMPRODUCT((Model!$B$4:$F$4*Inputs!$B$47:$F$47/1000-E$3*Model!$B$4:$F$4/1000)*(1-Inputs!$B$5)*Model!$B$34:$F$34)-SUMPRODUCT(Model!$B$28:$F$28*Model!$B$33:$F$33)+SUMPRODUCT((('Tail 2032-2049'!$E$3:$E$20-E$3*Model!$F$5/1000-Inputs!$B$29*Model!$F$5/Model!$F$3)*(1-Inputs!$B$5)+Inputs!$B$5*Inputs!$B$30)*'Tail 2032-2049'!$H$3:$H$20)+(Model!$F$4*($A7-E$3)/1000-Inputs!$B$29*(1-Model!$F$5/Model!$F$3))*(1-Inputs!$B$5)*SUM('Tail 2032-2049'!$I$3:$I$20)+((Model!$F$4*($A7-E$3)/1000-Inputs!$B$29*(1-Model!$F$5/Model!$F$3))+Model!$F$5*($A7-E$3)/1000)*(1-Inputs!$B$5)/Inputs!$B$7/(1+Inputs!$B$7)^(Inputs!$B$31-2026)-Inputs!$B$10-Inputs!$B$11-Inputs!$B$13*(1-Inputs!$B$5)/Inputs!$B$6-Inputs!$B$14)/Inputs!$B$4 -> 16.050719
A8: 4.5 | B8: =(SUMPRODUCT(((Model!$B$8:$F$8+Model!$B$9:$F$9-B$3*Model!$B$5:$F$5/1000)*(1-Inputs!$B$5)+Inputs!$B$5*Model!$B$18:$F$18)*Model!$B$33:$F$33)+SUMPRODUCT((Model!$B$4:$F$4*Inputs!$B$47:$F$47/1000-B$3*Model!$B$4:$F$4/1000)*(1-Inputs!$B$5)*Model!$B$34:$F$34)-SUMPRODUCT(Model!$B$28:$F$28*Model!$B$33:$F$33)+SUMPRODUCT((('Tail 2032-2049'!$E$3:$E$20-B$3*Model!$F$5/1000-Inputs!$B$29*Model!$F$5/Model!$F$3)*(1-Inputs!$B$5)+Inputs!$B$5*Inputs!$B$30)*'Tail 2032-2049'!$H$3:$H$20)+(Model!$F$4*($A8-B$3)/1000-Inputs!$B$29*(1-Model!$F$5/Model!$F$3))*(1-Inputs!$B$5)*SUM('Tail 2032-2049'!$I$3:$I$20)+((Model!$F$4*($A8-B$3)/1000-Inputs!$B$29*(1-Model!$F$5/Model!$F$3))+Model!$F$5*($A8-B$3)/1000)*(1-Inputs!$B$5)/Inputs!$B$7/(1+Inputs!$B$7)^(Inputs!$B$31-2026)-Inputs!$B$10-Inputs!$B$11-Inputs!$B$13*(1-Inputs!$B$5)/Inputs!$B$6-Inputs!$B$14)/Inputs!$B$4 -> 10.082776 | C8: =(SUMPRODUCT(((Model!$B$8:$F$8+Model!$B$9:$F$9-C$3*Model!$B$5:$F$5/1000)*(1-Inputs!$B$5)+Inputs!$B$5*Model!$B$18:$F$18)*Model!$B$33:$F$33)+SUMPRODUCT((Model!$B$4:$F$4*Inputs!$B$47:$F$47/1000-C$3*Model!$B$4:$F$4/1000)*(1-Inputs!$B$5)*Model!$B$34:$F$34)-SUMPRODUCT(Model!$B$28:$F$28*Model!$B$33:$F$33)+SUMPRODUCT((('Tail 2032-2049'!$E$3:$E$20-C$3*Model!$F$5/1000-Inputs!$B$29*Model!$F$5/Model!$F$3)*(1-Inputs!$B$5)+Inputs!$B$5*Inputs!$B$30)*'Tail 2032-2049'!$H$3:$H$20)+(Model!$F$4*($A8-C$3)/1000-Inputs!$B$29*(1-Model!$F$5/Model!$F$3))*(1-Inputs!$B$5)*SUM('Tail 2032-2049'!$I$3:$I$20)+((Model!$F$4*($A8-C$3)/1000-Inputs!$B$29*(1-Model!$F$5/Model!$F$3))+Model!$F$5*($A8-C$3)/1000)*(1-Inputs!$B$5)/Inputs!$B$7/(1+Inputs!$B$7)^(Inputs!$B$31-2026)-Inputs!$B$10-Inputs!$B$11-Inputs!$B$13*(1-Inputs!$B$5)/Inputs!$B$6-Inputs!$B$14)/Inputs!$B$4 -> 13.437774 | D8: =(SUMPRODUCT(((Model!$B$8:$F$8+Model!$B$9:$F$9-D$3*Model!$B$5:$F$5/1000)*(1-Inputs!$B$5)+Inputs!$B$5*Model!$B$18:$F$18)*Model!$B$33:$F$33)+SUMPRODUCT((Model!$B$4:$F$4*Inputs!$B$47:$F$47/1000-D$3*Model!$B$4:$F$4/1000)*(1-Inputs!$B$5)*Model!$B$34:$F$34)-SUMPRODUCT(Model!$B$28:$F$28*Model!$B$33:$F$33)+SUMPRODUCT((('Tail 2032-2049'!$E$3:$E$20-D$3*Model!$F$5/1000-Inputs!$B$29*Model!$F$5/Model!$F$3)*(1-Inputs!$B$5)+Inputs!$B$5*Inputs!$B$30)*'Tail 2032-2049'!$H$3:$H$20)+(Model!$F$4*($A8-D$3)/1000-Inputs!$B$29*(1-Model!$F$5/Model!$F$3))*(1-Inputs!$B$5)*SUM('Tail 2032-2049'!$I$3:$I$20)+((Model!$F$4*($A8-D$3)/1000-Inputs!$B$29*(1-Model!$F$5/Model!$F$3))+Model!$F$5*($A8-D$3)/1000)*(1-Inputs!$B$5)/Inputs!$B$7/(1+Inputs!$B$7)^(Inputs!$B$31-2026)-Inputs!$B$10-Inputs!$B$11-Inputs!$B$13*(1-Inputs!$B$5)/Inputs!$B$6-Inputs!$B$14)/Inputs!$B$4 -> 15.917555 | E8: =(SUMPRODUCT(((Model!$B$8:$F$8+Model!$B$9:$F$9-E$3*Model!$B$5:$F$5/1000)*(1-Inputs!$B$5)+Inputs!$B$5*Model!$B$18:$F$18)*Model!$B$33:$F$33)+SUMPRODUCT((Model!$B$4:$F$4*Inputs!$B$47:$F$47/1000-E$3*Model!$B$4:$F$4/1000)*(1-Inputs!$B$5)*Model!$B$34:$F$34)-SUMPRODUCT(Model!$B$28:$F$28*Model!$B$33:$F$33)+SUMPRODUCT((('Tail 2032-2049'!$E$3:$E$20-E$3*Model!$F$5/1000-Inputs!$B$29*Model!$F$5/Model!$F$3)*(1-Inputs!$B$5)+Inputs!$B$5*Inputs!$B$30)*'Tail 2032-2049'!$H$3:$H$20)+(Model!$F$4*($A8-E$3)/1000-Inputs!$B$29*(1-Model!$F$5/Model!$F$3))*(1-Inputs!$B$5)*SUM('Tail 2032-2049'!$I$3:$I$20)+((Model!$F$4*($A8-E$3)/1000-Inputs!$B$29*(1-Model!$F$5/Model!$F$3))+Model!$F$5*($A8-E$3)/1000)*(1-Inputs!$B$5)/Inputs!$B$7/(1+Inputs!$B$7)^(Inputs!$B$31-2026)-Inputs!$B$10-Inputs!$B$11-Inputs!$B$13*(1-Inputs!$B$5)/Inputs!$B$6-Inputs!$B$14)/Inputs!$B$4 -> 18.105597
A9: 5.19 | B9: =(SUMPRODUCT(((Model!$B$8:$F$8+Model!$B$9:$F$9-B$3*Model!$B$5:$F$5/1000)*(1-Inputs!$B$5)+Inputs!$B$5*Model!$B$18:$F$18)*Model!$B$33:$F$33)+SUMPRODUCT((Model!$B$4:$F$4*Inputs!$B$47:$F$47/1000-B$3*Model!$B$4:$F$4/1000)*(1-Inputs!$B$5)*Model!$B$34:$F$34)-SUMPRODUCT(Model!$B$28:$F$28*Model!$B$33:$F$33)+SUMPRODUCT((('Tail 2032-2049'!$E$3:$E$20-B$3*Model!$F$5/1000-Inputs!$B$29*Model!$F$5/Model!$F$3)*(1-Inputs!$B$5)+Inputs!$B$5*Inputs!$B$30)*'Tail 2032-2049'!$H$3:$H$20)+(Model!$F$4*($A9-B$3)/1000-Inputs!$B$29*(1-Model!$F$5/Model!$F$3))*(1-Inputs!$B$5)*SUM('Tail 2032-2049'!$I$3:$I$20)+((Model!$F$4*($A9-B$3)/1000-Inputs!$B$29*(1-Model!$F$5/Model!$F$3))+Model!$F$5*($A9-B$3)/1000)*(1-Inputs!$B$5)/Inputs!$B$7/(1+Inputs!$B$7)^(Inputs!$B$31-2026)-Inputs!$B$10-Inputs!$B$11-Inputs!$B$13*(1-Inputs!$B$5)/Inputs!$B$6-Inputs!$B$14)/Inputs!$B$4 -> 12.918507 | C9: =(SUMPRODUCT(((Model!$B$8:$F$8+Model!$B$9:$F$9-C$3*Model!$B$5:$F$5/1000)*(1-Inputs!$B$5)+Inputs!$B$5*Model!$B$18:$F$18)*Model!$B$33:$F$33)+SUMPRODUCT((Model!$B$4:$F$4*Inputs!$B$47:$F$47/1000-C$3*Model!$B$4:$F$4/1000)*(1-Inputs!$B$5)*Model!$B$34:$F$34)-SUMPRODUCT(Model!$B$28:$F$28*Model!$B$33:$F$33)+SUMPRODUCT((('Tail 2032-2049'!$E$3:$E$20-C$3*Model!$F$5/1000-Inputs!$B$29*Model!$F$5/Model!$F$3)*(1-Inputs!$B$5)+Inputs!$B$5*Inputs!$B$30)*'Tail 2032-2049'!$H$3:$H$20)+(Model!$F$4*($A9-C$3)/1000-Inputs!$B$29*(1-Model!$F$5/Model!$F$3))*(1-Inputs!$B$5)*SUM('Tail 2032-2049'!$I$3:$I$20)+((Model!$F$4*($A9-C$3)/1000-Inputs!$B$29*(1-Model!$F$5/Model!$F$3))+Model!$F$5*($A9-C$3)/1000)*(1-Inputs!$B$5)/Inputs!$B$7/(1+Inputs!$B$7)^(Inputs!$B$31-2026)-Inputs!$B$10-Inputs!$B$11-Inputs!$B$13*(1-Inputs!$B$5)/Inputs!$B$6-Inputs!$B$14)/Inputs!$B$4 -> 16.273505 | D9: =(SUMPRODUCT(((Model!$B$8:$F$8+Model!$B$9:$F$9-D$3*Model!$B$5:$F$5/1000)*(1-Inputs!$B$5)+Inputs!$B$5*Model!$B$18:$F$18)*Model!$B$33:$F$33)+SUMPRODUCT((Model!$B$4:$F$4*Inputs!$B$47:$F$47/1000-D$3*Model!$B$4:$F$4/1000)*(1-Inputs!$B$5)*Model!$B$34:$F$34)-SUMPRODUCT(Model!$B$28:$F$28*Model!$B$33:$F$33)+SUMPRODUCT((('Tail 2032-2049'!$E$3:$E$20-D$3*Model!$F$5/1000-Inputs!$B$29*Model!$F$5/Model!$F$3)*(1-Inputs!$B$5)+Inputs!$B$5*Inputs!$B$30)*'Tail 2032-2049'!$H$3:$H$20)+(Model!$F$4*($A9-D$3)/1000-Inputs!$B$29*(1-Model!$F$5/Model!$F$3))*(1-Inputs!$B$5)*SUM('Tail 2032-2049'!$I$3:$I$20)+((Model!$F$4*($A9-D$3)/1000-Inputs!$B$29*(1-Model!$F$5/Model!$F$3))+Model!$F$5*($A9-D$3)/1000)*(1-Inputs!$B$5)/Inputs!$B$7/(1+Inputs!$B$7)^(Inputs!$B$31-2026)-Inputs!$B$10-Inputs!$B$11-Inputs!$B$13*(1-Inputs!$B$5)/Inputs!$B$6-Inputs!$B$14)/Inputs!$B$4 -> 18.753287 | E9: =(SUMPRODUCT(((Model!$B$8:$F$8+Model!$B$9:$F$9-E$3*Model!$B$5:$F$5/1000)*(1-Inputs!$B$5)+Inputs!$B$5*Model!$B$18:$F$18)*Model!$B$33:$F$33)+SUMPRODUCT((Model!$B$4:$F$4*Inputs!$B$47:$F$47/1000-E$3*Model!$B$4:$F$4/1000)*(1-Inputs!$B$5)*Model!$B$34:$F$34)-SUMPRODUCT(Model!$B$28:$F$28*Model!$B$33:$F$33)+SUMPRODUCT((('Tail 2032-2049'!$E$3:$E$20-E$3*Model!$F$5/1000-Inputs!$B$29*Model!$F$5/Model!$F$3)*(1-Inputs!$B$5)+Inputs!$B$5*Inputs!$B$30)*'Tail 2032-2049'!$H$3:$H$20)+(Model!$F$4*($A9-E$3)/1000-Inputs!$B$29*(1-Model!$F$5/Model!$F$3))*(1-Inputs!$B$5)*SUM('Tail 2032-2049'!$I$3:$I$20)+((Model!$F$4*($A9-E$3)/1000-Inputs!$B$29*(1-Model!$F$5/Model!$F$3))+Model!$F$5*($A9-E$3)/1000)*(1-Inputs!$B$5)/Inputs!$B$7/(1+Inputs!$B$7)^(Inputs!$B$31-2026)-Inputs!$B$10-Inputs!$B$11-Inputs!$B$13*(1-Inputs!$B$5)/Inputs!$B$6-Inputs!$B$14)/Inputs!$B$4 -> 20.941329
A10: 6 | B10: =(SUMPRODUCT(((Model!$B$8:$F$8+Model!$B$9:$F$9-B$3*Model!$B$5:$F$5/1000)*(1-Inputs!$B$5)+Inputs!$B$5*Model!$B$18:$F$18)*Model!$B$33:$F$33)+SUMPRODUCT((Model!$B$4:$F$4*Inputs!$B$47:$F$47/1000-B$3*Model!$B$4:$F$4/1000)*(1-Inputs!$B$5)*Model!$B$34:$F$34)-SUMPRODUCT(Model!$B$28:$F$28*Model!$B$33:$F$33)+SUMPRODUCT((('Tail 2032-2049'!$E$3:$E$20-B$3*Model!$F$5/1000-Inputs!$B$29*Model!$F$5/Model!$F$3)*(1-Inputs!$B$5)+Inputs!$B$5*Inputs!$B$30)*'Tail 2032-2049'!$H$3:$H$20)+(Model!$F$4*($A10-B$3)/1000-Inputs!$B$29*(1-Model!$F$5/Model!$F$3))*(1-Inputs!$B$5)*SUM('Tail 2032-2049'!$I$3:$I$20)+((Model!$F$4*($A10-B$3)/1000-Inputs!$B$29*(1-Model!$F$5/Model!$F$3))+Model!$F$5*($A10-B$3)/1000)*(1-Inputs!$B$5)/Inputs!$B$7/(1+Inputs!$B$7)^(Inputs!$B$31-2026)-Inputs!$B$10-Inputs!$B$11-Inputs!$B$13*(1-Inputs!$B$5)/Inputs!$B$6-Inputs!$B$14)/Inputs!$B$4 -> 16.247409 | C10: =(SUMPRODUCT(((Model!$B$8:$F$8+Model!$B$9:$F$9-C$3*Model!$B$5:$F$5/1000)*(1-Inputs!$B$5)+Inputs!$B$5*Model!$B$18:$F$18)*Model!$B$33:$F$33)+SUMPRODUCT((Model!$B$4:$F$4*Inputs!$B$47:$F$47/1000-C$3*Model!$B$4:$F$4/1000)*(1-Inputs!$B$5)*Model!$B$34:$F$34)-SUMPRODUCT(Model!$B$28:$F$28*Model!$B$33:$F$33)+SUMPRODUCT((('Tail 2032-2049'!$E$3:$E$20-C$3*Model!$F$5/1000-Inputs!$B$29*Model!$F$5/Model!$F$3)*(1-Inputs!$B$5)+Inputs!$B$5*Inputs!$B$30)*'Tail 2032-2049'!$H$3:$H$20)+(Model!$F$4*($A10-C$3)/1000-Inputs!$B$29*(1-Model!$F$5/Model!$F$3))*(1-Inputs!$B$5)*SUM('Tail 2032-2049'!$I$3:$I$20)+((Model!$F$4*($A10-C$3)/1000-Inputs!$B$29*(1-Model!$F$5/Model!$F$3))+Model!$F$5*($A10-C$3)/1000)*(1-Inputs!$B$5)/Inputs!$B$7/(1+Inputs!$B$7)^(Inputs!$B$31-2026)-Inputs!$B$10-Inputs!$B$11-Inputs!$B$13*(1-Inputs!$B$5)/Inputs!$B$6-Inputs!$B$14)/Inputs!$B$4 -> 19.602407 | D10: =(SUMPRODUCT(((Model!$B$8:$F$8+Model!$B$9:$F$9-D$3*Model!$B$5:$F$5/1000)*(1-Inputs!$B$5)+Inputs!$B$5*Model!$B$18:$F$18)*Model!$B$33:$F$33)+SUMPRODUCT((Model!$B$4:$F$4*Inputs!$B$47:$F$47/1000-D$3*Model!$B$4:$F$4/1000)*(1-Inputs!$B$5)*Model!$B$34:$F$34)-SUMPRODUCT(Model!$B$28:$F$28*Model!$B$33:$F$33)+SUMPRODUCT((('Tail 2032-2049'!$E$3:$E$20-D$3*Model!$F$5/1000-Inputs!$B$29*Model!$F$5/Model!$F$3)*(1-Inputs!$B$5)+Inputs!$B$5*Inputs!$B$30)*'Tail 2032-2049'!$H$3:$H$20)+(Model!$F$4*($A10-D$3)/1000-Inputs!$B$29*(1-Model!$F$5/Model!$F$3))*(1-Inputs!$B$5)*SUM('Tail 2032-2049'!$I$3:$I$20)+((Model!$F$4*($A10-D$3)/1000-Inputs!$B$29*(1-Model!$F$5/Model!$F$3))+Model!$F$5*($A10-D$3)/1000)*(1-Inputs!$B$5)/Inputs!$B$7/(1+Inputs!$B$7)^(Inputs!$B$31-2026)-Inputs!$B$10-Inputs!$B$11-Inputs!$B$13*(1-Inputs!$B$5)/Inputs!$B$6-Inputs!$B$14)/Inputs!$B$4 -> 22.082189 | E10: =(SUMPRODUCT(((Model!$B$8:$F$8+Model!$B$9:$F$9-E$3*Model!$B$5:$F$5/1000)*(1-Inputs!$B$5)+Inputs!$B$5*Model!$B$18:$F$18)*Model!$B$33:$F$33)+SUMPRODUCT((Model!$B$4:$F$4*Inputs!$B$47:$F$47/1000-E$3*Model!$B$4:$F$4/1000)*(1-Inputs!$B$5)*Model!$B$34:$F$34)-SUMPRODUCT(Model!$B$28:$F$28*Model!$B$33:$F$33)+SUMPRODUCT((('Tail 2032-2049'!$E$3:$E$20-E$3*Model!$F$5/1000-Inputs!$B$29*Model!$F$5/Model!$F$3)*(1-Inputs!$B$5)+Inputs!$B$5*Inputs!$B$30)*'Tail 2032-2049'!$H$3:$H$20)+(Model!$F$4*($A10-E$3)/1000-Inputs!$B$29*(1-Model!$F$5/Model!$F$3))*(1-Inputs!$B$5)*SUM('Tail 2032-2049'!$I$3:$I$20)+((Model!$F$4*($A10-E$3)/1000-Inputs!$B$29*(1-Model!$F$5/Model!$F$3))+Model!$F$5*($A10-E$3)/1000)*(1-Inputs!$B$5)/Inputs!$B$7/(1+Inputs!$B$7)^(Inputs!$B$31-2026)-Inputs!$B$10-Inputs!$B$11-Inputs!$B$13*(1-Inputs!$B$5)/Inputs!$B$6-Inputs!$B$14)/Inputs!$B$4 -> 24.270231
